Workbook

Sheet Terms
A1: ID | B1: Term | C1: Also Known As | D1: Category | E1: Applies To Lines | F1: Plain-English Definition | G1: Example | H1: Where You'll See It | I1: Most Relevant For | J1: Difficulty | K1: Usage Frequency | L1: Related Terms | M1: US Notes
A2: section-1035-exchange | B2: 1035 Exchange | D2: Line-Specific | E2: Life | F2: A tax-free swap of one life insurance or annuity policy for another under IRS Section 1035. | G2: You exchange an old annuity for a new one without paying tax. | H2: Application form | I2: Individuals, Underwriters, Product Owners | J2: Advanced | K2: Low | L2: replacement
A3: seven-pay-test | B3: 7-Pay Test | D3: Line-Specific | E3: Life | F3: A federal tax test that checks whether premiums in the first seven years exceed limits, which would make a policy a MEC. | G3: Premiums above the 7-pay limit trigger MEC status. | H3: Policy administration system | I3: Developers, Underwriters | J3: Advanced | K3: Low | L3: modified-endowment-contract
A4: a-plus-report | B4: A-PLUS Report | C4: Automated Property Loss Underwriting System | D4: Underwriting | E4: Property, Motor | F4: A Verisk database report of past property and auto claims, similar to CLUE. | G4: An underwriter checks A-PLUS for prior losses. | H4: Underwriting system | I4: Developers, Underwriters | J4: Advanced | K4: Low | L4: clue-report, loss-history
A5: aais | B5: AAIS | C5: American Association of Insurance Services | D5: Technology | E5: Property, Commercial, Marine/Aviation/Transit, Agriculture | F5: An advisory organization, owned by member insurers, that provides standard forms and loss costs, similar to ISO. | G5: A mutual insurer uses AAIS farm forms. | H5: Policy document | I5: Underwriters, Product Owners | J5: Advanced | K5: Low | L5: iso
A6: ab-initio | B6: Ab Initio | D6: Legal/Latin | E6: All | F6: Latin for 'from the beginning'. A policy void ab initio is treated as if it never existed. | G6: A policy obtained by fraud is rescinded ab initio and the premium refunded. | H6: Policy document | I6: Developers, Underwriters | J6: Advanced | K6: Low | L6: rescission, void-policy
A7: abandonment | B7: Abandonment | D7: Claims | E7: Marine/Aviation/Transit | F7: Giving up ownership of damaged property to the insurer in exchange for a total loss payment. | G7: A shipowner abandons a wrecked vessel to the insurers. | H7: Policy document | I7: Underwriters | J7: Advanced | K7: Low | L7: constructive-total-loss, salvage | M7: Property policies usually say the insured cannot abandon property to the insurer.
A8: accelerated-death-benefit-rider | B8: Accelerated Death Benefit Rider | C8: Living Benefits Rider | D8: Line-Specific | E8: Life | F8: A rider that lets you receive part of the death benefit early if you are terminally, chronically or critically ill. | G8: You receive 50% of the benefit after a terminal diagnosis. | H8: Policy document | I8: Individuals, Underwriters, Product Owners | J8: Intermediate | K8: Medium | L8: rider, chronic-illness-rider
A9: accelerated-underwriting | B9: Accelerated Underwriting | D9: Underwriting | E9: Life | F9: Using data and algorithms to approve some life applicants without a medical exam. | G9: A healthy 30-year-old is approved in minutes without blood tests. | H9: Underwriting system | I9: Developers, Underwriters, Product Owners | J9: Intermediate | K9: Medium | L9: medical-underwriting, paramedical-exam, predictive-model
A10: accident | B10: Accident | D10: Policy Wording | E10: All | F10: A sudden, unexpected and unintended event that causes injury or damage. | G10: Slipping on ice and breaking an arm is an accident. | H10: Policy document | I10: Individuals, Underwriters | J10: Beginner | K10: High | L10: occurrence, accidental-death-and-dismemberment
A11: accident-forgiveness | B11: Accident Forgiveness | D11: Underwriting | E11: Motor | F11: A feature where your first at-fault accident doesn't raise your premium. | G11: No surcharge after your first fender-bender. | H11: Policy document | I11: Individuals, Product Owners | J11: Beginner | K11: Low | L11: driving-record-points | M11: Banned in some states such as California.
A12: accident-insurance | B12: Accident Insurance | D12: Line-Specific | E12: Health | F12: Insurance paying set amounts for injuries from accidents, such as fractures or ER visits. | G12: $500 for a broken arm. | H12: Policy document | I12: Individuals, Product Owners | J12: Beginner | K12: Medium | L12: accidental-death-and-dismemberment, critical-illness-insurance
A13: accident-year | B13: Accident Year | C13: AY | D13: Finance & Actuarial | E13: Property, Casualty/Liability, Motor, Commercial | F13: Grouping of losses by the year the accident happened. | G13: All losses from accidents in 2024 belong to AY 2024. | H13: Financial statements | I13: Developers, Product Owners | J13: Advanced | K13: Medium | L13: policy-year, calendar-year, underwriting-year
A14: accidental-death-and-dismemberment | B14: Accidental Death and Dismemberment | C14: AD&D | D14: Line-Specific | E14: Life, Health | F14: Insurance paying if you die or lose a limb, eyesight or hearing in an accident. | G14: AD&D pays 50% of the benefit for loss of one hand. | H14: Policy document | I14: Individuals, Developers, Product Owners | J14: Intermediate | K14: Medium | L14: accident-insurance, accidental-death-benefit-rider
A15: accidental-death-benefit-rider | B15: Accidental Death Benefit Rider | C15: ADB; Double Indemnity | D15: Line-Specific | E15: Life | F15: A rider that pays an extra benefit if death results from an accident. | G15: An extra $250,000 paid for accidental death. | H15: Policy document | I15: Individuals, Underwriters | J15: Intermediate | K15: Medium | L15: rider, accidental-death-and-dismemberment
A16: aggregation | B16: Accumulation | C16: Aggregation; Concentration Risk | D16: Underwriting | E16: Property, Commercial, Financial Lines, Reinsurance | F16: The build-up of many insured risks exposed to the same event. | G16: Too many insured homes in one coastal county. | H16: Underwriting system | I16: Underwriters, Product Owners | J16: Advanced | K16: Low | L16: catastrophe-model, probable-maximum-loss
A17: accumulation-phase | B17: Accumulation Phase | D17: Line-Specific | E17: Life | F17: The period when money in a deferred annuity grows before payouts start. | G17: Contributions grow tax-deferred in the accumulation phase. | H17: Policy document | I17: Individuals, Developers | J17: Intermediate | K17: Low | L17: deferred-annuity, annuitization
A18: acord | B18: ACORD | C18: Association for Cooperative Operations Research and Development | D18: Technology | E18: All | F18: A nonprofit that sets data standards (XML, JSON, forms) for exchanging insurance information. | G18: Agency software sends ACORD XML to a carrier. | H18: Data exchange/integration specs | I18: Developers, Product Owners | J18: Intermediate | K18: Medium | L18: acord-forms, acord-al3
A19: acord-al3 | B19: ACORD AL3 | D19: Technology | E19: All | F19: An older ACORD standard file format used to download policy data from carriers to agency systems. | G19: A carrier sends daily AL3 downloads to agents. | H19: Data exchange/integration specs | I19: Developers | J19: Advanced | K19: Low | L19: acord
A20: acord-forms | B20: ACORD Forms | D20: Technology | E20: All | F20: Standardized application and certificate forms used across the US industry, such as ACORD 25 (certificate of liability insurance) and ACORD 125. | G20: A broker fills out ACORD 125 and 126 for a commercial GL submission. | H20: Application form, Agent/broker communications | I20: Developers, Underwriters, Product Owners | J20: Intermediate | K20: Medium | L20: acord, certificate-of-insurance, application
A21: acquisition-costs | B21: Acquisition Costs | D21: Finance & Actuarial | E21: All | F21: Costs of getting new business, such as commissions, marketing and underwriting. | G21: Commissions and premium taxes are acquisition costs. | H21: Financial statements | I21: Developers, Product Owners | J21: Intermediate | K21: Medium | L21: expense-ratio, deferred-acquisition-costs, commission
A22: act-of-god | B22: Act of God | C22: Force of Nature | D22: Legal/Latin | E22: All | F22: A natural event outside human control, such as a flood, earthquake or lightning. | G22: Lightning striking a barn is an act of God. | H22: Policy document | I22: Individuals, Underwriters | J22: Beginner | K22: Medium | L22: force-majeure, peril, catastrophe
A23: activities-of-daily-living | B23: Activities of Daily Living | C23: ADLs | D23: Line-Specific | E23: Life, Health | F23: Basic self-care tasks, usually bathing, dressing, eating, toileting, continence and transferring, used to trigger long-term care benefits. | G23: Needing help with two ADLs qualifies you for LTC benefits. | H23: Policy document, Claim documents | I23: Individuals, Underwriters | J23: Intermediate | K23: Medium | L23: long-term-care-insurance, chronic-illness-rider
A24: actual-cash-value | B24: Actual Cash Value | C24: ACV | D24: Core Concept | E24: Property, Motor | F24: The value of property at the time of loss: replacement cost minus depreciation. | G24: A 5-year-old TV that costs $1,000 new may be worth $400 ACV. | H24: Policy document, Claim documents | I24: Individuals, Developers, Underwriters, Product Owners | J24: Beginner | K24: High | L24: replacement-cost, depreciation, indemnity | M24: Some states define ACV by statute or case law, including whether labor can be depreciated.
A25: actual-production-history | B25: Actual Production History | C25: APH | D25: Underwriting | E25: Agriculture | F25: A farmer's historical average yields, used to set crop insurance guarantees. | G25: A 10-year APH of 180 bushels per acre. | H25: Underwriting system | I25: Developers, Underwriters | J25: Advanced | K25: Low | L25: multi-peril-crop-insurance
A26: actuarial-value | B26: Actuarial Value | C26: AV | D26: Finance & Actuarial | E26: Health | F26: The percentage of total average costs for covered benefits that a plan pays. | G26: A silver plan has about 70% actuarial value. | H26: Product specification | I26: Developers, Product Owners | J26: Advanced | K26: Low | L26: metal-tiers
A27: actuary | B27: Actuary | D27: Finance & Actuarial | E27: All | F27: A professional who uses math and statistics to price insurance, set reserves and measure risk. | G27: An actuary calculates how much to charge 30-year-old non-smokers for term life. | I27: Developers, Underwriters, Product Owners | J27: Beginner | K27: Medium | L27: law-of-large-numbers, reserves | M27: Credentialed by the CAS (property/casualty) or SOA (life/health).
A28: additional-insured | B28: Additional Insured | C28: AI | D28: Policy Wording | E28: Property, Casualty/Liability, Commercial | F28: A person or company added to someone else's policy so they are also protected, often required by a contract. | G28: A landlord requires a tenant's liability policy to list the landlord as an additional insured. | H28: Policy document, Declarations page | I28: Developers, Underwriters, Product Owners | J28: Intermediate | K28: High | L28: named-insured, certificate-of-insurance, endorsement
A29: additional-living-expense | B29: Additional Living Expense | C29: ALE | D29: Policy Wording | E29: Property | F29: The increase in living costs, such as rent and meals, after a covered loss forces you out of your home. | G29: Paying $2,000/month rent while your home is rebuilt. | H29: Policy document | I29: Individuals, Underwriters | J29: Beginner | K29: Medium | L29: loss-of-use, fair-rental-value
A30: additional-premium | B30: Additional Premium | C30: AP | D30: Lifecycle | E30: All | F30: Extra premium charged because of a mid-term change that increases the risk. | G30: Adding a pool to your home policy costs $80 additional premium. | H30: Billing statement | I30: Developers, Underwriters | J30: Beginner | K30: Medium | L30: return-premium, mid-term-adjustment
A31: administrative-services-only | B31: Administrative Services Only | C31: ASO | D31: Distribution | E31: Health | F31: An arrangement where an insurer or TPA processes claims for a self-funded plan but doesn't take the risk. | G31: A big insurer handles claims for an employer's plan under an ASO contract. | I31: Developers, Product Owners | J31: Advanced | K31: Low | L31: self-funded-plan, third-party-administrator
A32: admitted-insurer | B32: Admitted Insurer | C32: Admitted Carrier; Licensed Insurer | D32: Regulation | E32: All | F32: An insurer licensed by a state to do business there, subject to its rate and form rules and covered by its guaranty fund. | G32: Most personal auto insurers are admitted. | H32: Regulatory filings | I32: Individuals, Developers, Underwriters, Product Owners | J32: Intermediate | K32: Medium | L32: non-admitted-insurer, guaranty-fund, surplus-lines
A33: adverse-action-notice | B33: Adverse Action Notice | D33: Regulation | E33: All | F33: A notice explaining that a consumer report influenced a decision to decline or charge more. | G33: A letter says your insurance score affected your premium. | H33: Regulatory filings | I33: Developers, Underwriters | J33: Intermediate | K33: Low | L33: fcra
A34: adverse-development-cover | B34: Adverse Development Cover | C34: ADC | D34: Reinsurance | E34: Reinsurance, Alternative Risk Transfer | F34: Reinsurance that pays if reserves for past claims turn out to be too low. | G34: Covers reserve growth above $500M on old liability claims. | H34: Reinsurance contract | I34: Product Owners | J34: Advanced | K34: Low | L34: portfolio-transfer, reserve-development
A35: adverse-selection | B35: Adverse Selection | C35: Anti-Selection | D35: Underwriting | E35: All | F35: When people who are more likely to have a loss are more likely to buy insurance, making the pool riskier. | G35: People who know they need surgery sign up for health insurance right before. | H35: Underwriting system | I35: Underwriters, Product Owners | J35: Intermediate | K35: Medium | L35: underwriting, open-enrollment-period, individual-mandate
A36: aerial-imagery | B36: Aerial Imagery | D36: Technology | E36: Property, Commercial | F36: Satellite or aircraft images used to assess roofs, trees and hazards without visiting. | G36: An insurer spots a damaged roof from imagery. | H36: Underwriting system | I36: Developers, Underwriters | J36: Intermediate | K36: Low | L36: inspection, third-party-data | M36: Some states restrict non-renewals based solely on aerial images.
A37: affinity-group | B37: Affinity Group | C37: Affinity Program | D37: Distribution | E37: All | F37: Insurance sold to members of an organization, like alumni or professional associations, often at group rates. | G37: A bar association sponsors a professional liability program. | I37: Underwriters, Product Owners | J37: Intermediate | K37: Low | L37: group-insurance, embedded-insurance
A38: affordable-care-act | B38: Affordable Care Act | C38: ACA; Obamacare | D38: Regulation | E38: Health | F38: A 2010 federal law that reformed US health insurance, including marketplaces, subsidies, essential benefits and bans on pre-existing condition exclusions. | G38: You can't be denied a plan because of diabetes. | H38: Regulatory filings | I38: Individuals, Developers, Underwriters, Product Owners | J38: Beginner | K38: High | L38: health-insurance-marketplace, essential-health-benefits, pre-existing-condition, premium-tax-credit
A39: age-nearest-birthday | B39: Age Nearest Birthday | C39: ANB; Age Last Birthday (ALB) | D39: Underwriting | E39: Life | F39: Two ways insurers define age: the age at your nearest birthday, or at your last birthday. | G39: At 35 and 7 months you're 36 ANB but 35 ALB. | H39: Rating engine | I39: Developers, Underwriters | J39: Advanced | K39: Low | L39: issue-age
A40: agency-bill | B40: Agency Bill | D40: Distribution | E40: Property, Casualty/Liability, Commercial | F40: The agent bills and collects premium from the client, then pays the insurer net of commission. | G40: A commercial client pays the agency, not the carrier. | H40: Billing statement | I40: Developers, Underwriters | J40: Intermediate | K40: Medium | L40: direct-bill
A41: agency-management-system | B41: Agency Management System | C41: AMS | D41: Technology | E41: All | F41: Software agencies use to manage clients, policies, commissions and documents. | G41: An agency uses Applied Epic or Vertafore AMS360. | I41: Developers, Product Owners | J41: Intermediate | K41: Medium | L41: acord, comparative-rater
A42: insurance-agent | B42: Agent | C42: Insurance Agent; Producer | D42: Distribution | E42: All | F42: A licensed person or firm who sells insurance on behalf of one or more insurers. | G42: A local State Farm agent sells you home and auto insurance. | H42: Agent/broker communications | I42: Individuals, Developers, Underwriters, Product Owners | J42: Beginner | K42: High | L42: captive-agent, independent-agent, broker, producer | M42: Agents must hold a state license for each line and state.
A43: agent-errors-and-omissions | B43: Agent E&O | C43: Agents Errors and Omissions | D43: Distribution | E43: Financial Lines | F43: Professional liability coverage for insurance agents against claims of mistakes in placing coverage. | G43: A client sues an agent who forgot to add flood coverage. | I43: Underwriters, Product Owners | J43: Intermediate | K43: Low | L43: errors-and-omissions-insurance
A44: aggregate-excess-of-loss | B44: Aggregate Excess of Loss | C44: Stop Loss Reinsurance | D44: Reinsurance | E44: Health, Agriculture, Reinsurance | F44: Reinsurance that pays when total losses for a year exceed a set amount or loss ratio. | G44: Pays when the crop portfolio's loss ratio exceeds 110%. | H44: Reinsurance contract | I44: Underwriters, Product Owners | J44: Advanced | K44: Low | L44: excess-of-loss, stop-loss-insurance
A45: aggregate-limit | B45: Aggregate Limit | C45: General Aggregate | D45: Core Concept | E45: Casualty/Liability, Commercial, Specialty, Financial Lines | F45: The most the insurer will pay for all claims combined during one policy period. | G45: A business has a $2M aggregate; after paying $2M in claims this year, no more claims are paid until renewal. | H45: Declarations page, Policy document | I45: Developers, Underwriters, Product Owners | J45: Intermediate | K45: High | L45: limit-of-liability, per-occurrence-limit, products-completed-operations-aggregate
A46: aggregate-stop-loss | B46: Aggregate Stop-Loss | D46: Line-Specific | E46: Health | F46: Stop-loss that pays when the total claims for the whole group exceed a set amount. | G46: Pays when total claims exceed 125% of expected. | H46: Policy document | I46: Underwriters, Product Owners | J46: Advanced | K46: Low | L46: stop-loss-insurance, specific-stop-loss
A47: aggregator | B47: Aggregator | C47: Comparison Site; Lead Generator | D47: Distribution | E47: Life, Health, Property, Motor | F47: A website that collects quotes from many insurers for comparison. | G47: A site shows 10 auto quotes side by side. | I47: Individuals, Developers, Product Owners | J47: Beginner | K47: Medium | L47: direct-writer, lead-generation
A48: agreed-value | B48: Agreed Value | C48: Stated Amount | D48: Policy Wording | E48: Property, Motor, Marine/Aviation/Transit, Specialty | F48: A value the insured and insurer agree on in advance, which is paid for a total loss without arguing about depreciation. | G48: A classic car is insured for an agreed value of $60,000. | H48: Declarations page, Policy document | I48: Individuals, Underwriters, Product Owners | J48: Intermediate | K48: Medium | L48: actual-cash-value, stated-value, valued-policy
A49: aircraft-liability | B49: Aircraft Liability | D49: Policy Wording | E49: Marine/Aviation/Transit | F49: Covers injury to passengers and third parties caused by aircraft operations. | G49: A plane crash injures people on the ground. | H49: Policy document | I49: Underwriters | J49: Advanced | K49: Low | L49: aviation-insurance
A50: aleatory-contract | B50: Aleatory Contract | D50: Legal/Latin | E50: All | F50: A contract where what each side gives may be very unequal and depends on an uncertain event. | G50: You pay $800 in premium and might receive $300,000 if your house burns down, or nothing. | I50: Underwriters, Product Owners | J50: Advanced | K50: Low | L50: unilateral-contract, contract-of-adhesion
A51: allocated-loss-adjustment-expense | B51: Allocated Loss Adjustment Expense | C51: ALAE; DCC (Defense and Cost Containment) | D51: Finance & Actuarial | E51: All | F51: Claim expenses that can be tied to a specific claim, such as defense lawyers and experts. | G51: $20,000 paid to a defense firm on one lawsuit is ALAE. | H51: Financial statements | I51: Developers, Underwriters | J51: Advanced | K51: Medium | L51: loss-adjustment-expense, unallocated-loss-adjustment-expense | M51: NAIC statutory reporting uses the term DCC.
A52: allowed-amount | B52: Allowed Amount | C52: Eligible Expense; Negotiated Rate | D52: Line-Specific | E52: Health | F52: The maximum amount a plan will pay for a covered service, often a negotiated rate with in-network providers. | G52: A doctor bills $300; the allowed amount is $180. | H52: Explanation of benefits | I52: Individuals, Developers | J52: Intermediate | K52: Medium | L52: balance-billing, explanation-of-benefits, usual-customary-reasonable
A53: alternative-risk-transfer | B53: Alternative Risk Transfer | C53: ART | D53: Core Concept | E53: Alternative Risk Transfer | F53: Ways of managing or financing risk outside traditional insurance, such as captives, cat bonds and self-insurance. | G53: A company forms a captive to insure its own risks. | I53: Underwriters, Product Owners | J53: Intermediate | K53: Low | L53: captive-insurance-company, catastrophe-bond, risk-retention-group
A54: am-best | B54: AM Best | D54: Finance & Actuarial | E54: All | F54: A credit rating agency specializing in insurance companies. | G54: AM Best rates an insurer 'A+ (Superior)'. | I54: Underwriters, Product Owners | J54: Intermediate | K54: Low | L54: financial-strength-rating
A55: ambiguity | B55: Ambiguity | D55: Legal/Latin | E55: All | F55: Policy wording that can reasonably be read in more than one way. | G55: 'Flood' might or might not include sewer backup; that is an ambiguity. | H55: Policy document | I55: Underwriters, Product Owners | J55: Intermediate | K55: Low | L55: contra-proferentem, reasonable-expectations-doctrine
A56: annual-maximum | B56: Annual Maximum | C56: Annual Benefit Maximum | D56: Line-Specific | E56: Health | F56: The most a plan (commonly dental) will pay in a year. | G56: A dental plan's $1,500 annual maximum. | H56: Policy document | I56: Individuals, Developers | J56: Beginner | K56: Medium | L56: dental-insurance, limit-of-liability | M56: ACA bans annual dollar limits on essential health benefits, but dental maximums remain for adults.
A57: annual-renewable-term | B57: Annual Renewable Term | C57: ART; Yearly Renewable Term; YRT | D57: Line-Specific | E57: Life, Reinsurance | F57: Term insurance that renews each year with rising premiums as you age; YRT is also a common life reinsurance basis. | G57: Premium rises every year on a YRT policy. | H57: Policy document, Reinsurance contract | I57: Developers, Underwriters | J57: Intermediate | K57: Low | L57: level-term, term-life-insurance
A58: annual-statement | B58: Annual Statement | C58: Yellow Book; Blue Book | D58: Finance & Actuarial | E58: All | F58: The detailed yearly financial report each insurer files with regulators using NAIC formats. | G58: The annual statement includes Schedule P for reserves. | H58: Financial statements, Regulatory filings | I58: Developers, Underwriters, Product Owners | J58: Advanced | K58: Medium | L58: statutory-accounting-principles, schedule-p | M58: P&C statements are called the Yellow Book; life statements the Blue Book.
A59: annuitant | B59: Annuitant | D59: Line-Specific | E59: Life | F59: The person whose life expectancy determines annuity payments; often also the owner. | G59: The annuitant is 65 and receives monthly income. | H59: Policy document | I59: Individuals, Developers | J59: Beginner | K59: Medium | L59: annuity
A60: annuitization | B60: Annuitization | D60: Line-Specific | E60: Life | F60: Converting the annuity's value into a stream of regular payments. | G60: You annuitize at age 70 for life income. | H60: Policy document | I60: Individuals, Developers | J60: Intermediate | K60: Medium | L60: annuity, payout-option
A61: annuity | B61: Annuity | D61: Line-Specific | E61: Life | F61: A contract with an insurer where you pay money in and receive regular income, often for life. | G61: You pay $100,000 and receive $550 a month for life. | H61: Policy document | I61: Individuals, Developers, Underwriters, Product Owners | J61: Beginner | K61: High | L61: fixed-annuity, variable-annuity, immediate-annuity, deferred-annuity
A62: anti-concurrent-causation-clause | B62: Anti-Concurrent Causation Clause | C62: ACC Clause | D62: Policy Wording | E62: Property | F62: Wording that excludes a loss if an excluded cause contributed in any way, even if a covered cause also contributed. | G62: Flood damage is excluded even though wind also contributed. | H62: Policy document | I62: Underwriters | J62: Advanced | K62: Low | L62: concurrent-causation, exclusion | M62: Not enforced in some states, such as California and Washington.
A63: anti-money-laundering | B63: Anti-Money Laundering | C63: AML | D63: Regulation | E63: Life | F63: Rules requiring insurers selling certain life and annuity products to detect and report money laundering. | G63: A large single premium paid in cash triggers review. | H63: Regulatory filings | I63: Developers, Underwriters, Product Owners | J63: Intermediate | K63: Low | L63: know-your-customer, ofac | M63: Covered life insurers have AML program obligations under the Bank Secrecy Act.
A64: any-occupation | B64: Any Occupation | C64: Any Occ | D64: Line-Specific | E64: Health | F64: A disability definition that pays only if you can't do any job suited to your education and experience. | G64: After 2 years, LTD switches to any-occupation. | H64: Policy document | I64: Individuals, Underwriters | J64: Advanced | K64: Low | L64: own-occupation
A65: appeal | B65: Appeal | C65: Internal Appeal | D65: Claims | E65: All | F65: A request asking your insurer to reconsider a denied claim or decision. | G65: You appeal a denied MRI with a letter from your doctor. | H65: Claim documents | I65: Individuals, Developers | J65: Beginner | K65: High | L65: external-review, claim-denial
A66: application | B66: Application | C66: App; Proposal Form | D66: Lifecycle | E66: All | F66: The form you fill out to request insurance, giving information the insurer uses to decide and price. | G66: A life application asks about your health, hobbies and income. | H66: Application form | I66: Individuals, Developers, Underwriters, Product Owners | J66: Beginner | K66: High | L66: quote, underwriting, representation
A67: appointed-actuary | B67: Appointed Actuary | C67: Statement of Actuarial Opinion | D67: Finance & Actuarial | E67: All | F67: The actuary named by an insurer's board to give the regulator an opinion on the adequacy of its reserves. | G67: The appointed actuary signs the annual reserve opinion. | H67: Financial statements, Regulatory filings | I67: Product Owners | J67: Advanced | K67: Low | L67: actuary, reserves
A68: appointment | B68: Appointment | C68: Carrier Appointment | D68: Distribution | E68: All | F68: Official authorization from an insurer for an agent to represent it, often filed with the state. | G68: An agent is appointed with five carriers. | H68: Regulatory filings | I68: Developers, Underwriters, Product Owners | J68: Intermediate | K68: Medium | L68: insurance-agent, producer-license | M68: Most states require insurers to file appointments.
A69: appraisal-clause | B69: Appraisal Clause | C69: Appraisal | D69: Claims | E69: Property, Motor | F69: A process for settling disagreements about the amount of a loss, using independent appraisers and an umpire. | G69: You and the insurer disagree on the roof repair cost, so each hires an appraiser. | H69: Policy document | I69: Individuals, Underwriters | J69: Intermediate | K69: Medium | L69: umpire, dispute-resolution, claim-settlement
A70: arbitration-clause | B70: Arbitration Clause | D70: Policy Wording | E70: All | F70: A clause requiring disputes to be settled by a private arbitrator instead of a court. | G70: A reinsurance dispute goes to a panel of three arbitrators. | H70: Policy document, Reinsurance contract | I70: Underwriters, Product Owners | J70: Intermediate | K70: Medium | L70: appraisal-clause, dispute-resolution
A71: asbestos-and-environmental | B71: Asbestos and Environmental | C71: A&E | D71: Finance & Actuarial | E71: Casualty/Liability | F71: Long-tail liability claims from asbestos exposure and pollution that have cost insurers heavily for decades. | G71: An insurer increases A&E reserves. | H71: Financial statements | I71: Underwriters, Product Owners | J71: Advanced | K71: Low | L71: long-tail, run-off
A72: assigned-risk-plan | B72: Assigned Risk Plan | C72: Automobile Insurance Plan | D72: Regulation | E72: Motor, Commercial | F72: A residual market plan that assigns hard-to-insure drivers or employers to insurers. | G72: A high-risk driver is assigned to an insurer by the state plan. | H72: Regulatory filings | I72: Individuals, Underwriters | J72: Intermediate | K72: Low | L72: residual-market
A73: assignment | B73: Assignment | D73: Policy Wording | E73: All | F73: Transferring rights under a policy to someone else. | G73: A life policyowner assigns the policy to a bank as loan collateral. | H73: Policy document | I73: Developers, Underwriters | J73: Intermediate | K73: Low | L73: assignment-of-benefits
A74: assignment-of-benefits | B74: Assignment of Benefits | C74: AOB | D74: Claims | E74: Health, Property | F74: A document that lets a contractor or provider bill the insurer directly and pursue the claim. | G74: A water mitigation company has you sign an AOB and then bills your insurer. | H74: Claim documents | I74: Individuals, Developers, Underwriters | J74: Intermediate | K74: Medium | L74: assignment, claim | M74: Florida restricted AOB for property claims in 2019 and 2022 after abuse; health providers routinely take AOB.
A75: assumed-premium | B75: Assumed Premium | D75: Reinsurance | E75: Reinsurance | F75: Premium a reinsurer receives for risk it takes on from another insurer. | G75: A reinsurer books $10M assumed premium. | H75: Financial statements | I75: Developers, Product Owners | J75: Advanced | K75: Low | L75: ceded-premium
A76: attachment-point | B76: Attachment Point | D76: Reinsurance | E76: Property, Casualty/Liability, Financial Lines, Reinsurance | F76: The loss amount at which an excess or reinsurance layer starts to pay. | G76: An excess policy attaching at $10M pays once losses exceed $10M. | H76: Reinsurance contract, Declarations page | I76: Underwriters, Product Owners | J76: Advanced | K76: Medium | L76: layer, retention, excess-insurance
A77: attained-age | B77: Attained Age | D77: Underwriting | E77: Life, Health | F77: The insured's current age, used for premiums that rise with age. | G77: Medigap attained-age pricing rises each year. | H77: Policy document | I77: Developers, Underwriters | J77: Intermediate | K77: Low | L77: issue-age, community-rating
A78: attorney-in-fact | B78: Attorney-in-Fact | D78: Core Concept | E78: All | F78: The company that manages a reciprocal exchange on behalf of its members. | G78: Erie Indemnity is attorney-in-fact for Erie Insurance Exchange. | I78: Product Owners | J78: Advanced | K78: Low | L78: reciprocal-exchange
A79: auditable-policy | B79: Auditable Policy | D79: Lifecycle | E79: Casualty/Liability, Commercial | F79: A policy whose final premium is determined by an audit after it ends. | G79: Workers' comp and GL on payroll or sales basis are auditable. | H79: Policy administration system | I79: Developers, Underwriters | J79: Intermediate | K79: Low | L79: premium-audit, deposit-premium
A80: auto-adjudication | B80: Auto-Adjudication | D80: Technology | E80: All | F80: Automatic processing of claims by a system without human review. | G80: 90% of routine doctor visit claims are auto-adjudicated. | H80: Claims system | I80: Developers, Product Owners | J80: Intermediate | K80: Low | L80: claim-adjudication, straight-through-processing
A81: automatic-coverage | B81: Automatic Coverage | C81: Newly Acquired Coverage | D81: Policy Wording | E81: Property, Motor, Commercial | F81: Temporary coverage for newly acquired property until you report it to the insurer. | G81: A new car is covered for 14–30 days until you add it. | H81: Policy document | I81: Individuals, Underwriters | J81: Intermediate | K81: Low | L81: endorsement
A82: automatic-premium-loan | B82: Automatic Premium Loan | C82: APL | D82: Line-Specific | E82: Life | F82: A feature that automatically borrows from cash value to pay a missed premium to prevent lapse. | G82: A missed payment is covered by an APL. | H82: Policy document | I82: Individuals, Developers | J82: Intermediate | K82: Low | L82: policy-loan, nonforfeiture-options
A83: average | B83: Average | C83: Condition of Average | D83: Policy Wording | E83: Property, Marine/Aviation/Transit | F83: A clause, similar to coinsurance, that cuts claim payments proportionally when property is underinsured. | G83: Marine cargo underinsured by half receives half of the loss. | H83: Policy document | I83: Underwriters | J83: Advanced | K83: Low | L83: coinsurance-clause, underinsurance, general-average | M83: Common in marine and London-market wordings used in the US.
A84: average-annual-loss | B84: Average Annual Loss | C84: AAL | D84: Finance & Actuarial | E84: Property, Reinsurance | F84: The expected yearly loss from catastrophes, averaged over many simulated years. | G84: A portfolio's hurricane AAL is $12M. | H84: Financial statements | I84: Developers, Product Owners | J84: Advanced | K84: Low | L84: catastrophe-model
A85: aviation-insurance | B85: Aviation Insurance | D85: Line-Specific | E85: Marine/Aviation/Transit, Specialty | F85: Coverage for aircraft hull damage and liability for passengers and third parties. | G85: An airline insures its fleet. | H85: Policy document | I85: Underwriters, Product Owners | J85: Intermediate | K85: Low | L85: hull-insurance, aircraft-liability
A86: backdating | B86: Backdating | D86: Lifecycle | E86: Life | F86: Setting a life policy's date earlier than the application date to get a lower age-based premium. | G86: Backdating by 3 months to 'save age'. | H86: Policy administration system | I86: Developers, Underwriters | J86: Advanced | K86: Low | L86: issue-age | M86: Most states limit backdating to 6 months.
A87: bad-faith | B87: Bad Faith | D87: Legal/Latin | E87: All | F87: When an insurer unreasonably fails to meet its duties, such as denying or delaying a valid claim without good reason. | G87: An insurer ignores a reasonable settlement offer within limits, and the insured faces a large judgment. | H87: Claim documents | I87: Underwriters, Product Owners | J87: Advanced | K87: Medium | L87: unfair-claims-settlement-practices, duty-to-defend, excess-verdict | M87: Bad faith law is state-specific; some states allow extra-contractual and punitive damages.
A88: bail-bond | B88: Bail Bond | D88: Line-Specific | E88: Specialty, Financial Lines | F88: A surety bond guaranteeing a defendant will appear in court. | G88: A bail agent posts bond for a defendant's release. | I88: Individuals, Underwriters | J88: Intermediate | K88: Low | L88: surety-bond | M88: Commercial bail is banned or largely eliminated in a few states, such as Illinois, Kentucky, Oregon and Wisconsin.
A89: balance-billing | B89: Balance Billing | D89: Line-Specific | E89: Health | F89: When a provider bills you for the difference between their charge and the allowed amount. | G89: An out-of-network doctor bills you $120 above what your plan paid. | H89: Explanation of benefits | I89: Individuals, Developers | J89: Intermediate | K89: Medium | L89: allowed-amount, no-surprises-act, out-of-network
A90: bancassurance | B90: Bancassurance | D90: Distribution | E90: Life, Property | F90: Selling insurance through banks. | G90: A bank offers life insurance to mortgage customers. | I90: Product Owners | J90: Intermediate | K90: Low | L90: embedded-insurance | M90: Less common in the US than elsewhere because of historic banking law limits, partly lifted by the Gramm-Leach-Bliley Act (1999).
A91: base-rate | B91: Base Rate | D91: Underwriting | E91: All | F91: The starting rate before adjustments for the specific risk's features. | G91: A base rate for a territory is then adjusted for driver age and vehicle type. | H91: Rating engine | I91: Developers, Underwriters, Product Owners | J91: Intermediate | K91: Medium | L91: rate, rating-factor, rating-algorithm
A92: basic-form | B92: Basic Form | C92: Basic Causes of Loss | D92: Policy Wording | E92: Property, Commercial | F92: A property coverage form covering a short list of perils such as fire, lightning, windstorm, hail, explosion and vandalism. | G92: A vacant building insured on a basic form. | H92: Policy document | I92: Underwriters, Product Owners | J92: Intermediate | K92: Low | L92: broad-form, special-form, named-perils
A93: beneficiary | B93: Beneficiary | D93: Core Concept | E93: Life, Health, Financial Lines | F93: The person or organization that receives the money when a claim is paid, especially from a life insurance policy. | G93: A husband names his wife as beneficiary of his life policy. | H93: Application form, Policy document | I93: Individuals, Developers, Underwriters | J93: Beginner | K93: High | L93: contingent-beneficiary, primary-beneficiary, policyholder
A94: benefit-period | B94: Benefit Period | D94: Line-Specific | E94: Life, Health | F94: How long benefits are paid, or (in Medicare) the span of a hospital or skilled nursing episode. | G94: An LTD benefit period to age 65. | H94: Policy document | I94: Individuals, Developers | J94: Intermediate | K94: Medium | L94: elimination-period
A95: betterment | B95: Betterment | D95: Claims | E95: Property, Motor | F95: A deduction for when a repair makes property better than before the loss. | G95: New tires installed on a car with worn tires may carry a betterment charge. | H95: Claims system | I95: Individuals, Underwriters | J95: Intermediate | K95: Low | L95: depreciation, indemnity
A96: bid-bond | B96: Bid Bond | D96: Line-Specific | E96: Specialty, Financial Lines | F96: A bond guaranteeing that a winning bidder will sign the contract and provide performance and payment bonds. | G96: A contractor submits a bid bond with a public project bid. | H96: Policy document | I96: Underwriters | J96: Intermediate | K96: Low | L96: performance-bond
A97: billing-system | B97: Billing System | D97: Technology | E97: All | F97: Software that manages invoicing, payment plans, collections and commissions for policies. | G97: The billing system issues a cancellation notice after missed payment. | H97: Billing statement | I97: Developers, Product Owners | J97: Intermediate | K97: Medium | L97: policy-administration-system, installment-plan
A98: binder | B98: Binder | C98: Cover Note | D98: Lifecycle | E98: All | F98: A temporary written agreement that coverage is in force until the policy is issued. | G98: A 30-day binder given to a mortgage lender at closing. | H98: Policy administration system | I98: Individuals, Developers, Underwriters | J98: Intermediate | K98: Medium | L98: binding, issuance | M98: State rules limit binder duration (often 90 days).
A99: binding | B99: Binding | C99: Bind | D99: Lifecycle | E99: All | F99: Putting coverage into effect, often before the formal policy is issued. | G99: Your agent binds coverage at noon so you can drive the new car home. | H99: Policy administration system | I99: Individuals, Developers, Underwriters, Product Owners | J99: Beginner | K99: High | L99: binder, quote, issuance
A100: binding-authority | B100: Binding Authority | C100: Delegated Authority | D100: Distribution | E100: All | F100: Permission given by an insurer to an agent or MGA to accept risks and issue coverage on its behalf. | G100: An MGA has authority to bind small restaurant policies. | I100: Developers, Underwriters, Product Owners | J100: Intermediate | K100: Medium | L100: managing-general-agent, underwriting-authority, binder
...

Sheet By Category
A1: Glossary Counts
A2: All counts are live formulas over the Terms sheet.
A4: Total terms | B4: =COUNTA(Terms!$A$2:$A$1017) -> 1016
A6: Category | B6: Terms | C6: % of Total | D6: Description
A7: Core Concept | B7: =COUNTIF(Terms!$D$2:$D$1017,"Core Concept") -> 55 | C7: =IF($B$4=0,0,B7/$B$4) -> 0.054133858 | D7: Foundational ideas that apply across insurance (premium, indemnity, risk, liability).
A8: Policy Wording | B8: =COUNTIF(Terms!$D$2:$D$1017,"Policy Wording") -> 158 | C8: =IF($B$4=0,0,B8/$B$4) -> 0.15551181 | D8: Parts, clauses and phrases found in the policy contract itself.
A9: Lifecycle | B9: =COUNTIF(Terms!$D$2:$D$1017,"Lifecycle") -> 40 | C9: =IF($B$4=0,0,B9/$B$4) -> 0.039370079 | D9: Stages and transactions in a policy's life: quote, bind, issue, change, renew, cancel.
A10: Underwriting | B10: =COUNTIF(Terms!$D$2:$D$1017,"Underwriting") -> 78 | C10: =IF($B$4=0,0,B10/$B$4) -> 0.076771654 | D10: Evaluating, selecting and pricing risks.
A11: Claims | B11: =COUNTIF(Terms!$D$2:$D$1017,"Claims") -> 59 | C11: =IF($B$4=0,0,B11/$B$4) -> 0.058070866 | D11: Reporting, investigating, valuing and settling losses.
A12: Distribution | B12: =COUNTIF(Terms!$D$2:$D$1017,"Distribution") -> 40 | C12: =IF($B$4=0,0,B12/$B$4) -> 0.039370079 | D12: How insurance is sold: agents, brokers, MGAs, channels and commissions.
A13: Finance & Actuarial | B13: =COUNTIF(Terms!$D$2:$D$1017,"Finance & Actuarial") -> 93 | C13: =IF($B$4=0,0,B13/$B$4) -> 0.091535433 | D13: Accounting, reserving, pricing math and financial metrics.
A14: Regulation | B14: =COUNTIF(Terms!$D$2:$D$1017,"Regulation") -> 91 | C14: =IF($B$4=0,0,B14/$B$4) -> 0.089566929 | D14: US federal and state laws, regulators and compliance requirements.
A15: Reinsurance | B15: =COUNTIF(Terms!$D$2:$D$1017,"Reinsurance") -> 41 | C15: =IF($B$4=0,0,B15/$B$4) -> 0.040354331 | D15: Insurance for insurers, layers, treaties and capital-market risk transfer structures.
A16: Legal/Latin | B16: =COUNTIF(Terms!$D$2:$D$1017,"Legal/Latin") -> 49 | C16: =IF($B$4=0,0,B16/$B$4) -> 0.048228346 | D16: Legal doctrines and Latin phrases seen in policies, claims and court decisions.
A17: Technology | B17: =COUNTIF(Terms!$D$2:$D$1017,"Technology") -> 62 | C17: =IF($B$4=0,0,B17/$B$4) -> 0.061023622 | D17: Systems, data standards and codes developers meet on insurance projects.
A18: Line-Specific | B18: =COUNTIF(Terms!$D$2:$D$1017,"Line-Specific") -> 250 | C18: =IF($B$4=0,0,B18/$B$4) -> 0.24606299 | D18: Terms that belong mainly to one line of insurance (life, health, auto, marine, cyber, crop, etc.).
A19: Subtotal | B19: =SUM(B7:B18) -> 1016
A21: Applies To Line | B21: Terms | C21: % of Total | D21: Description
A22: All | B22: =COUNTIF(Terms!$E$2:$E$1017,"All") -> 318 | C22: =IF($B$4=0,0,B22/$B$4) -> 0.31299213 | D22: Applies across all lines of insurance.
A23: Life | B23: =COUNTIF(Terms!$E$2:$E$1017,"*Life*") -> 144 | C23: =IF($B$4=0,0,B23/$B$4) -> 0.14173228 | D23: Life insurance and annuities.
A24: Health | B24: =COUNTIF(Terms!$E$2:$E$1017,"*Health*") -> 163 | C24: =IF($B$4=0,0,B24/$B$4) -> 0.16043307 | D24: Medical, dental, vision, disability, long-term care and supplemental health.
A25: Property | B25: =COUNTIF(Terms!$E$2:$E$1017,"*Property*") -> 186 | C25: =IF($B$4=0,0,B25/$B$4) -> 0.18307087 | D25: Homes, buildings, contents, flood, earthquake and other property.
A26: Casualty/Liability | B26: =COUNTIF(Terms!$E$2:$E$1017,"*Casualty/Liability*") -> 124 | C26: =IF($B$4=0,0,B26/$B$4) -> 0.12204724 | D26: Legal liability to others: general, product, umbrella, workers' comp liability, etc.
A27: Motor | B27: =COUNTIF(Terms!$E$2:$E$1017,"*Motor*") -> 112 | C27: =IF($B$4=0,0,B27/$B$4) -> 0.11023622 | D27: Personal and commercial auto.
A28: Commercial | B28: =COUNTIF(Terms!$E$2:$E$1017,"*Commercial*") -> 168 | C28: =IF($B$4=0,0,B28/$B$4) -> 0.16535433 | D28: Business insurance packages and coverages.
A29: Marine/Aviation/Transit | B29: =COUNTIF(Terms!$E$2:$E$1017,"*Marine/Aviation/Transit*") -> 46 | C29: =IF($B$4=0,0,B29/$B$4) -> 0.045275591 | D29: Ocean and inland marine, cargo, hull, aviation and goods in transit.
A30: Specialty | B30: =COUNTIF(Terms!$E$2:$E$1017,"*Specialty*") -> 61 | C30: =IF($B$4=0,0,B30/$B$4) -> 0.06003937 | D30: Niche risks: travel, pet, event, title, K&R, space, etc.
A31: Financial Lines | B31: =COUNTIF(Terms!$E$2:$E$1017,"*Financial Lines*") -> 81 | C31: =IF($B$4=0,0,B31/$B$4) -> 0.079724409 | D31: D&O, E&O/professional, cyber, crime, fidelity, surety, credit and mortgage.
A32: Agriculture | B32: =COUNTIF(Terms!$E$2:$E$1017,"*Agriculture*") -> 22 | C32: =IF($B$4=0,0,B32/$B$4) -> 0.021653543 | D32: Crop, livestock and farm insurance.
A33: Social/Government | B33: =COUNTIF(Terms!$E$2:$E$1017,"*Social/Government*") -> 28 | C33: =IF($B$4=0,0,B33/$B$4) -> 0.027559055 | D33: Government and social programs: Medicare, Medicaid, NFIP, SSDI, unemployment, state funds.
A34: Reinsurance | B34: =COUNTIF(Terms!$E$2:$E$1017,"*Reinsurance*") -> 57 | C34: =IF($B$4=0,0,B34/$B$4) -> 0.056102362 | D34: Insurance bought by insurers.
A35: Alternative Risk Transfer | B35: =COUNTIF(Terms!$E$2:$E$1017,"*Alternative Risk Transfer*") -> 14 | C35: =IF($B$4=0,0,B35/$B$4) -> 0.013779528 | D35: Captives, risk retention groups, cat bonds, ILS and parametric structures.
A36: A term can apply to several lines, so line counts overlap and do not sum to the total. 'All' counts terms tagged as applying to every line.
A38: Difficulty | B38: Terms | C38: % of Total | D38: Description
A39: Beginner | B39: =COUNTIF(Terms!$J$2:$J$1017,"Beginner") -> 230 | C39: =IF($B$4=0,0,B39/$B$4) -> 0.22637795 | D39: Everyday terms most policyholders will see.
A40: Intermediate | B40: =COUNTIF(Terms!$J$2:$J$1017,"Intermediate") -> 471 | C40: =IF($B$4=0,0,B40/$B$4) -> 0.46358268 | D40: Common professional terms; some industry context helps.
A41: Advanced | B41: =COUNTIF(Terms!$J$2:$J$1017,"Advanced") -> 315 | C41: =IF($B$4=0,0,B41/$B$4) -> 0.31003937 | D41: Specialist terms used by underwriters, actuaries, lawyers or reinsurance professionals.
A42: Subtotal | B42: =SUM(B39:B41) -> 1016
A44: Usage Frequency | B44: Terms | C44: % of Total | D44: Description
A45: High | B45: =COUNTIF(Terms!$K$2:$K$1017,"High") -> 142 | C45: =IF($B$4=0,0,B45/$B$4) -> 0.13976378 | D45: Everyday words almost everyone in US insurance meets constantly (policy, premium, claim, deductible, renewal).
A46: Medium | B46: =COUNTIF(Terms!$K$2:$K$1017,"Medium") -> 420 | C46: =IF($B$4=0,0,B46/$B$4) -> 0.41338583 | D46: Common within specific lines, roles or documents, but not universal (subrogation, endorsement, binder, loss ratio).
A47: Low | B47: =COUNTIF(Terms!$K$2:$K$1017,"Low") -> 454 | C47: =IF($B$4=0,0,B47/$B$4) -> 0.44685039 | D47: Specialist, rare or niche terms (Latin maxims, obscure reinsurance/actuarial terms, rare forms or programs).
A48: Subtotal | B48: =SUM(B45:B47) -> 1016
A50: Most Relevant For | B50: Terms | C50: % of Total | D50: Description
A51: Individuals | B51: =COUNTIF(Terms!$I$2:$I$1017,"*Individuals*") -> 413 | C51: =IF($B$4=0,0,B51/$B$4) -> 0.40649606 | D51: Policyholders and consumers reading their own policy, bills and claim letters.
A52: Developers | B52: =COUNTIF(Terms!$I$2:$I$1017,"*Developers*") -> 516 | C52: =IF($B$4=0,0,B52/$B$4) -> 0.50787402 | D52: Engineers building or integrating insurance systems.
A53: Underwriters | B53: =COUNTIF(Terms!$I$2:$I$1017,"*Underwriters*") -> 735 | C53: =IF($B$4=0,0,B53/$B$4) -> 0.7234252 | D53: New underwriters and risk professionals (also useful for claims staff).
A54: Product Owners | B54: =COUNTIF(Terms!$I$2:$I$1017,"*Product Owners*") -> 596 | C54: =IF($B$4=0,0,B54/$B$4) -> 0.58661417 | D54: People defining insurance products, features, pricing and compliance requirements.
A55: A term can be relevant to several audiences, so these counts overlap.
A57: Category x Usage Frequency | B57: High | C57: Medium | D57: Low | E57: Total
A58: Core Concept | B58: =COUNTIFS(Terms!$D$2:$D$1017,$A58,Terms!$K$2:$K$1017,"High") -> 22 | C58: =COUNTIFS(Terms!$D$2:$D$1017,$A58,Terms!$K$2:$K$1017,"Medium") -> 15 | D58: =COUNTIFS(Terms!$D$2:$D$1017,$A58,Terms!$K$2:$K$1017,"Low") -> 18 | E58: =SUM(B58:D58) -> 55
A59: Policy Wording | B59: =COUNTIFS(Terms!$D$2:$D$1017,$A59,Terms!$K$2:$K$1017,"High") -> 23 | C59: =COUNTIFS(Terms!$D$2:$D$1017,$A59,Terms!$K$2:$K$1017,"Medium") -> 83 | D59: =COUNTIFS(Terms!$D$2:$D$1017,$A59,Terms!$K$2:$K$1017,"Low") -> 52 | E59: =SUM(B59:D59) -> 158
A60: Lifecycle | B60: =COUNTIFS(Terms!$D$2:$D$1017,$A60,Terms!$K$2:$K$1017,"High") -> 20 | C60: =COUNTIFS(Terms!$D$2:$D$1017,$A60,Terms!$K$2:$K$1017,"Medium") -> 15 | D60: =COUNTIFS(Terms!$D$2:$D$1017,$A60,Terms!$K$2:$K$1017,"Low") -> 5 | E60: =SUM(B60:D60) -> 40
A61: Underwriting | B61: =COUNTIFS(Terms!$D$2:$D$1017,$A61,Terms!$K$2:$K$1017,"High") -> 7 | C61: =COUNTIFS(Terms!$D$2:$D$1017,$A61,Terms!$K$2:$K$1017,"Medium") -> 49 | D61: =COUNTIFS(Terms!$D$2:$D$1017,$A61,Terms!$K$2:$K$1017,"Low") -> 22 | E61: =SUM(B61:D61) -> 78
A62: Claims | B62: =COUNTIFS(Terms!$D$2:$D$1017,$A62,Terms!$K$2:$K$1017,"High") -> 12 | C62: =COUNTIFS(Terms!$D$2:$D$1017,$A62,Terms!$K$2:$K$1017,"Medium") -> 24 | D62: =COUNTIFS(Terms!$D$2:$D$1017,$A62,Terms!$K$2:$K$1017,"Low") -> 23 | E62: =SUM(B62:D62) -> 59
A63: Distribution | B63: =COUNTIFS(Terms!$D$2:$D$1017,$A63,Terms!$K$2:$K$1017,"High") -> 6 | C63: =COUNTIFS(Terms!$D$2:$D$1017,$A63,Terms!$K$2:$K$1017,"Medium") -> 17 | D63: =COUNTIFS(Terms!$D$2:$D$1017,$A63,Terms!$K$2:$K$1017,"Low") -> 17 | E63: =SUM(B63:D63) -> 40
A64: Finance & Actuarial | B64: =COUNTIFS(Terms!$D$2:$D$1017,$A64,Terms!$K$2:$K$1017,"High") -> 4 | C64: =COUNTIFS(Terms!$D$2:$D$1017,$A64,Terms!$K$2:$K$1017,"Medium") -> 34 | D64: =COUNTIFS(Terms!$D$2:$D$1017,$A64,Terms!$K$2:$K$1017,"Low") -> 55 | E64: =SUM(B64:D64) -> 93
A65: Regulation | B65: =COUNTIFS(Terms!$D$2:$D$1017,$A65,Terms!$K$2:$K$1017,"High") -> 5 | C65: =COUNTIFS(Terms!$D$2:$D$1017,$A65,Terms!$K$2:$K$1017,"Medium") -> 29 | D65: =COUNTIFS(Terms!$D$2:$D$1017,$A65,Terms!$K$2:$K$1017,"Low") -> 57 | E65: =SUM(B65:D65) -> 91
A66: Reinsurance | B66: =COUNTIFS(Terms!$D$2:$D$1017,$A66,Terms!$K$2:$K$1017,"High") -> 1 | C66: =COUNTIFS(Terms!$D$2:$D$1017,$A66,Terms!$K$2:$K$1017,"Medium") -> 13 | D66: =COUNTIFS(Terms!$D$2:$D$1017,$A66,Terms!$K$2:$K$1017,"Low") -> 27 | E66: =SUM(B66:D66) -> 41
A67: Legal/Latin | B67: =COUNTIFS(Terms!$D$2:$D$1017,$A67,Terms!$K$2:$K$1017,"High") -> 2 | C67: =COUNTIFS(Terms!$D$2:$D$1017,$A67,Terms!$K$2:$K$1017,"Medium") -> 7 | D67: =COUNTIFS(Terms!$D$2:$D$1017,$A67,Terms!$K$2:$K$1017,"Low") -> 40 | E67: =SUM(B67:D67) -> 49
A68: Technology | B68: =COUNTIFS(Terms!$D$2:$D$1017,$A68,Terms!$K$2:$K$1017,"High") -> 6 | C68: =COUNTIFS(Terms!$D$2:$D$1017,$A68,Terms!$K$2:$K$1017,"Medium") -> 23 | D68: =COUNTIFS(Terms!$D$2:$D$1017,$A68,Terms!$K$2:$K$1017,"Low") -> 33 | E68: =SUM(B68:D68) -> 62
A69: Line-Specific | B69: =COUNTIFS(Terms!$D$2:$D$1017,$A69,Terms!$K$2:$K$1017,"High") -> 34 | C69: =COUNTIFS(Terms!$D$2:$D$1017,$A69,Terms!$K$2:$K$1017,"Medium") -> 111 | D69: =COUNTIFS(Terms!$D$2:$D$1017,$A69,Terms!$K$2:$K$1017,"Low") -> 105 | E69: =SUM(B69:D69) -> 250
A70: Total | B70: =SUM(B58:B69) -> 142 | C70: =SUM(C58:C69) -> 420 | D70: =SUM(D58:D69) -> 454 | E70: =SUM(E58:E69) -> 1016

Sheet README
A1: US Insurance Glossary
A2: Purpose | B2: Plain-English glossary of US insurance terms for people new to insurance: policyholders reading their policy, developers joining insurance projects, new underwriters and product owners. Built to be loaded into the learning app as glossary entries (see data/insurance-glossary.csv, which mirrors the Terms sheet).
A3: Scope | B3: US market only: US terminology, definitions and regulation (NAIC, state departments of insurance, admitted vs non-admitted/surplus lines, ACA, COBRA, ERISA, HIPAA, Medicare/Medicaid, ISO forms, NFIP, TRIA, federal crop insurance). Terms used only outside the US are excluded.
A4: Accuracy note | B4: Definitions are simplified for learning. Policy wording, state law and court decisions control actual coverage; always check the specific policy and state rules. State-specific facts in 'US Notes' reflect general knowledge as of 2026 and can change.
A5: Sorting | B5: Terms sheet is sorted alphabetically by Term (case-insensitive).
A7: COLUMNS (Terms sheet)
A8: ID | B8: Unique, stable, lowercase slug (a-z, 0-9, hyphens). Use as the primary key in the app.
A9: Term | B9: The term as it is most commonly written in the US.
A10: Also Known As | B10: Synonyms, abbreviations and acronym expansions, separated by semicolons (;). Alternative names are listed here rather than as separate rows.
A11: Category | B11: Exactly one value from the Category vocabulary below.
A12: Applies To Lines | B12: Comma-separated values from the Lines vocabulary below. 'All' means the term is general and applies across lines (used alone).
A13: Plain-English Definition | B13: One or two simple sentences, avoiding jargon. Never empty.
A14: Example | B14: A concrete, realistic illustration. Dollar figures are illustrative only.
A15: Where You'll See It | B15: Comma-separated values from the Where vocabulary below; may be blank for general concepts.
A16: Most Relevant For | B16: Comma-separated values from the Audience vocabulary below.
A17: Difficulty | B17: One value: Beginner, Intermediate or Advanced. How hard the term is to understand.
A18: Usage Frequency | B18: One value: High, Medium or Low. How often the term appears across US policy documents, quotes, claims and everyday industry work. Independent of Difficulty: a simple term can be Low and a technical one High. Never empty.
A19: Related Terms | B19: Comma-separated IDs of other rows in this sheet. Every ID is validated to exist.
A20: US Notes | B20: US-specific details such as state-by-state variations, federal rules or regulator names. Blank when not applicable.
A22: VOCABULARY: Category
A23: Core Concept | B23: Foundational ideas that apply across insurance (premium, indemnity, risk, liability).
A24: Policy Wording | B24: Parts, clauses and phrases found in the policy contract itself.
A25: Lifecycle | B25: Stages and transactions in a policy's life: quote, bind, issue, change, renew, cancel.
A26: Underwriting | B26: Evaluating, selecting and pricing risks.
A27: Claims | B27: Reporting, investigating, valuing and settling losses.
A28: Distribution | B28: How insurance is sold: agents, brokers, MGAs, channels and commissions.
A29: Finance & Actuarial | B29: Accounting, reserving, pricing math and financial metrics.
A30: Regulation | B30: US federal and state laws, regulators and compliance requirements.
A31: Reinsurance | B31: Insurance for insurers, layers, treaties and capital-market risk transfer structures.
A32: Legal/Latin | B32: Legal doctrines and Latin phrases seen in policies, claims and court decisions.
A33: Technology | B33: Systems, data standards and codes developers meet on insurance projects.
A34: Line-Specific | B34: Terms that belong mainly to one line of insurance (life, health, auto, marine, cyber, crop, etc.).
A36: VOCABULARY: Applies To Lines
A37: All | B37: Applies across all lines of insurance.
A38: Life | B38: Life insurance and annuities.
A39: Health | B39: Medical, dental, vision, disability, long-term care and supplemental health.
A40: Property | B40: Homes, buildings, contents, flood, earthquake and other property.
A41: Casualty/Liability | B41: Legal liability to others: general, product, umbrella, workers' comp liability, etc.
A42: Motor | B42: Personal and commercial auto.
A43: Commercial | B43: Business insurance packages and coverages.
A44: Marine/Aviation/Transit | B44: Ocean and inland marine, cargo, hull, aviation and goods in transit.
A45: Specialty | B45: Niche risks: travel, pet, event, title, K&R, space, etc.
A46: Financial Lines | B46: D&O, E&O/professional, cyber, crime, fidelity, surety, credit and mortgage.
A47: Agriculture | B47: Crop, livestock and farm insurance.
A48: Social/Government | B48: Government and social programs: Medicare, Medicaid, NFIP, SSDI, unemployment, state funds.
... A50: Alternative Risk Transfer | B50: Captives, risk retention groups, cat bonds, ILS and parametric structures.
A52: VOCABULARY: Most Relevant For
A53: Individuals | B53: Policyholders and consumers reading their own policy, bills and claim letters.
A54: Developers | B54: Engineers building or integrating insurance systems.
A55: Underwriters | B55: New underwriters and risk professionals (also useful for claims staff).
A56: Product Owners | B56: People defining insurance products, features, pricing and compliance requirements.
A58: VOCABULARY: Difficulty
A59: Beginner | B59: Everyday terms most policyholders will see.
A60: Intermediate | B60: Common professional terms; some industry context helps.
A61: Advanced | B61: Specialist terms used by underwriters, actuaries, lawyers or reinsurance professionals.
A63: VOCABULARY: Usage Frequency
A64: High | B64: Everyday words almost everyone in US insurance meets constantly (policy, premium, claim, deductible, renewal).
A65: Medium | B65: Common within specific lines, roles or documents, but not universal (subrogation, endorsement, binder, loss ratio).
A66: Low | B66: Specialist, rare or niche terms (Latin maxims, obscure reinsurance/actuarial terms, rare forms or programs).
A68: VOCABULARY: Where You'll See It
A69: Policy document
A70: Declarations page
A71: Application form
A72: Quote
A73: Claim documents
A74: Claims system
A75: Underwriting system
A76: Policy administration system
A77: Financial statements
A78: Regulatory filings
A79: Reinsurance contract
... A87: Data exchange/integration specs
A89: VALIDATION | B89: Checked by script before publishing: IDs unique and well-formed; term names unique; every Related Terms ID exists and is not a self-reference; Category, Lines, Audience, Difficulty, Usage Frequency and Where values come only from the vocabularies above; no empty Term or Definition; CSV matches the Terms sheet.
