Workbook

Sheet Tree
A1: ID | B1: Parent ID | C1: Level | D1: Name | E1: Also Known As | F1: Plain-English Description | G1: Example | H1: Personal/Commercial/Both | I1: US Notes | J1: Full Path
A2: life | C2: 1 | D2: Life Insurance | E2: Life coverage | F2: Pays money to chosen people (beneficiaries) when the insured person dies, and some types also build cash value you can use while alive. | G2: A parent buys a policy so their family can pay off the mortgage and college costs if the parent dies. | H2: Personal | I2: Regulated by states; policy forms filed with each state insurance department. State guaranty associations protect policyholders if an insurer fails (typically at least $300,000 death benefit). | J2: Life Insurance
A3: life.term | B3: life | C3: 2 | D3: Term Life | E3: Temporary life insurance | F3: Covers you only for a fixed period, such as 10, 20 or 30 years, and pays out only if you die within that period. It has no cash value, which makes it the cheapest life cover. | G3: A 30-year-old buys a 30-year term policy that matches the length of their mortgage. | H3: Personal | I3: The most common individual life product sold in the US by policy count. | J3: Life Insurance > Term Life
A4: life.term.level | B4: life.term | C4: 3 | D4: Level Term | E4: Guaranteed level term | F4: The death benefit and premium stay the same for the whole term (e.g. 10, 15, 20 or 30 years). | G4: A family buys $500,000 of cover that stays at $500,000 for 20 years. | H4: Personal | J4: Life Insurance > Term Life > Level Term
A5: life.term.decreasing | B5: life.term | C5: 3 | D5: Decreasing Term | E5: Mortgage protection insurance | F5: The death benefit shrinks over time, usually in line with a mortgage balance. | G5: A couple buys cover that falls each year as their mortgage is paid down. | H5: Personal | I5: Often marketed by mortgage servicers via direct mail. | J5: Life Insurance > Term Life > Decreasing Term
A6: life.term.art | B6: life.term | C6: 3 | D6: Annually Renewable Term (ART) | E6: Yearly renewable term (YRT) | F6: One-year cover that can be renewed each year without a new medical exam, with the premium rising as you age. | G6: A person needs cover for a short, uncertain period and renews year by year. | H6: Personal | I6: YRT is also the most common basis for life reinsurance. | J6: Life Insurance > Term Life > Annually Renewable Term (ART)
A7: life.term.convertible | B7: life.term | C7: 3 | D7: Convertible Term | F7: Term cover that can be switched into a permanent policy later without new medical questions. | G7: Someone buys cheap term cover now, planning to convert to whole life when their income grows. | H7: Personal | I7: Most US level term policies include a conversion privilege up to a set age. | J7: Life Insurance > Term Life > Convertible Term
A8: life.term.rop | B8: life.term | C8: 3 | D8: Return of Premium Term (ROP) | F8: Term cover that refunds the premiums you paid if you are still alive at the end of the term. It costs more than plain term. | G8: A buyer who dislikes "wasting" premiums picks a policy that returns them at the end of 30 years. | H8: Personal | J8: Life Insurance > Term Life > Return of Premium Term (ROP)
A9: life.term.credit_life | B9: life.term | C9: 3 | D9: Credit Life Insurance | E9: Credit insurance | F9: Pays off a specific loan if the borrower dies; often offered by the lender at the time of the loan. | G9: A car buyer is offered a policy that clears the auto loan if the buyer dies. | H9: Personal | I9: Rates and sales practices are tightly regulated by states; must be optional for the borrower. | J9: Life Insurance > Term Life > Credit Life Insurance
A10: life.permanent | B10: life | C10: 2 | D10: Permanent Life | E10: Cash value life insurance | F10: Covers you for your whole life as long as premiums are paid, and most types build a cash value you can borrow against or withdraw. | G10: A business owner buys permanent cover to leave money to heirs regardless of when they die. | H10: Personal | I10: Cash value grows tax-deferred if the policy meets the IRC Section 7702 definition of life insurance; overfunded policies become Modified Endowment Contracts (MECs). | J10: Life Insurance > Permanent Life
A11: life.permanent.whole | B11: life.permanent | C11: 3 | D11: Whole Life | E11: Ordinary life; Straight life | F11: Lifelong cover with fixed premiums, a guaranteed death benefit and a guaranteed cash value that grows slowly. | G11: A grandparent buys a whole life policy to leave a guaranteed sum to grandchildren. | H11: Personal | J11: Life Insurance > Permanent Life > Whole Life
A12: life.permanent.whole.participating | B12: life.permanent.whole | C12: 4 | D12: Participating Whole Life | E12: Par whole life; Dividend-paying whole life | F12: Whole life that may pay yearly dividends from the insurer's surplus, which can buy paid-up additions, reduce premiums or be taken as cash. | G12: A policyholder uses dividends from a mutual insurer to buy paid-up additions. | H12: Personal | I12: Sold mainly by mutual insurers (e.g. Northwestern Mutual, MassMutual, New York Life). Dividends are not guaranteed. | J12: Life Insurance > Permanent Life > Whole Life > Participating Whole Life
A13: life.permanent.whole.non_participating | B13: life.permanent.whole | C13: 4 | D13: Non-Participating Whole Life | E13: Non-par whole life | F13: Whole life with fixed guarantees and no dividends, usually at a lower premium. | G13: A buyer wants predictable costs without dividends. | H13: Personal | J13: Life Insurance > Permanent Life > Whole Life > Non-Participating Whole Life
A14: life.permanent.whole.limited_pay | B14: life.permanent.whole | C14: 4 | D14: Limited Pay Whole Life | E14: 10-pay; 20-pay; Paid-up at 65 | F14: Whole life where premiums are paid for a set number of years or until a certain age, but cover lasts for life. | G14: A 40-year-old pays for 20 years so nothing is owed in retirement. | H14: Personal | J14: Life Insurance > Permanent Life > Whole Life > Limited Pay Whole Life
A15: life.permanent.whole.single_premium | B15: life.permanent.whole | C15: 4 | D15: Single Premium Whole Life (SPWL) | F15: Whole life bought with one lump-sum payment. | G15: A retiree moves an inheritance into a single-premium policy for their heirs. | H15: Personal | I15: Usually a Modified Endowment Contract (MEC), so loans and withdrawals are taxed less favorably. | J15: Life Insurance > Permanent Life > Whole Life > Single Premium Whole Life (SPWL)
A16: life.permanent.whole.final_expense | B16: life.permanent.whole | C16: 4 | D16: Final Expense Insurance | E16: Burial insurance; Funeral insurance | F16: Small whole life policy (often $5,000-$25,000), with simplified medical questions, meant to cover funeral and end-of-life costs. | G16: A 70-year-old buys $10,000 of cover so their children won't have to pay for the funeral. | H16: Personal | I16: Heavily marketed to seniors aged 50-85. | J16: Life Insurance > Permanent Life > Whole Life > Final Expense Insurance
A17: life.permanent.whole.guaranteed_issue | B17: life.permanent.whole | C17: 4 | D17: Guaranteed Issue Whole Life | E17: Guaranteed acceptance life | F17: Whole life that accepts anyone in the eligible age range with no health questions; benefits are usually limited in the first two years (a "graded" death benefit). | G17: A person with serious health conditions who can't qualify elsewhere buys a small guaranteed policy. | H17: Personal | J17: Life Insurance > Permanent Life > Whole Life > Guaranteed Issue Whole Life
A18: life.permanent.whole.industrial | B18: life.permanent.whole | C18: 4 | D18: Industrial / Home Service Life | E18: Debit life | F18: Very small whole life policies historically sold door to door with weekly or monthly premium collection. | G18: A family in the 1950s paid a collector each week for a small burial policy. | H18: Personal | I18: Largely a legacy product; few new sales today. | J18: Life Insurance > Permanent Life > Whole Life > Industrial / Home Service Life
A19: life.permanent.universal | B19: life.permanent | C19: 3 | D19: Universal Life (UL) | E19: Flexible premium adjustable life | F19: Permanent cover with flexible premiums and an adjustable death benefit; the cash value earns interest credited in different ways depending on the type. | G19: A self-employed person with uneven income varies their payments each year. | H19: Personal | J19: Life Insurance > Permanent Life > Universal Life (UL)
A20: life.permanent.universal.current_assumption | B20: life.permanent.universal | C20: 4 | D20: Current Assumption Universal Life | E20: Traditional UL; Fixed UL | F20: The cash value earns an interest rate declared by the insurer, with a minimum guaranteed rate. | G20: A buyer wants flexible permanent cover with steady, insurer-declared interest. | H20: Personal | J20: Life Insurance > Permanent Life > Universal Life (UL) > Current Assumption Universal Life
A21: life.permanent.universal.gul | B21: life.permanent.universal | C21: 4 | D21: Guaranteed Universal Life (GUL) | E21: No-lapse guarantee UL | F21: UL built mainly for a guaranteed lifelong death benefit at the lowest cost, with little cash value. | G21: A retiree wants guaranteed cover to age 100+ for estate planning at a lower price than whole life. | H21: Personal | I21: Popular for estate planning; reserves governed by NAIC Actuarial Guideline 38 (AXXX). | J21: Life Insurance > Permanent Life > Universal Life (UL) > Guaranteed Universal Life (GUL)
A22: life.permanent.universal.iul | B22: life.permanent.universal | C22: 4 | D22: Indexed Universal Life (IUL) | E22: Equity-indexed UL; Fixed indexed UL | F22: Cash value earns interest linked to a stock market index (e.g. the S&P 500), subject to a cap and a floor (often 0%), so it doesn't lose value from market drops. | G22: A buyer wants some market-linked growth in their policy without direct stock market losses. | H22: Personal | I22: Illustrations are regulated by NAIC Actuarial Guideline 49-A. Not a registered security. | J22: Life Insurance > Permanent Life > Universal Life (UL) > Indexed Universal Life (IUL)
A23: life.permanent.universal.vul | B23: life.permanent.universal | C23: 4 | D23: Variable Universal Life (VUL) | F23: Cash value is invested in sub-accounts similar to mutual funds, so it can grow or lose value. | G23: An investor comfortable with risk picks equity funds inside their life policy. | H23: Personal | I23: Regulated as a security: sold with a prospectus by FINRA-registered representatives. | J23: Life Insurance > Permanent Life > Universal Life (UL) > Variable Universal Life (VUL)
A24: life.permanent.universal.survivorship | B24: life.permanent.universal | C24: 4 | D24: Survivorship Universal Life | E24: Second-to-die; Joint and last survivor | F24: Covers two people (usually spouses) and pays out only after both have died. | G24: A wealthy couple buys cover to pay estate taxes their heirs will owe after both die. | H24: Personal | I24: Often owned by an Irrevocable Life Insurance Trust (ILIT) to keep proceeds out of the taxable estate. | J24: Life Insurance > Permanent Life > Universal Life (UL) > Survivorship Universal Life
A25: life.permanent.variable_life | B25: life.permanent | C25: 3 | D25: Variable Life | E25: Variable whole life | F25: Permanent cover with fixed premiums where the cash value and possibly the death benefit depend on investment performance. | G25: A policyholder chooses investment sub-accounts inside a fixed-premium policy. | H25: Personal | I25: Regulated as a security (SEC/FINRA) as well as by state insurance departments. | J25: Life Insurance > Permanent Life > Variable Life
A26: life.annuities | B26: life | C26: 2 | D26: Annuities | F26: Turns a lump sum or series of payments into a stream of income, often for life. Annuities protect against outliving your savings rather than dying early. | G26: A retiree uses part of their savings to buy guaranteed monthly income for life. | H26: Personal | I26: Sold by life insurers; earnings grow tax-deferred. Fixed annuities are state-regulated; variable and registered index-linked annuities are also SEC/FINRA-regulated. | J26: Life Insurance > Annuities
A27: life.annuities.immediate | B27: life.annuities | C27: 3 | D27: Immediate Annuity | E27: Single Premium Immediate Annuity (SPIA); Income annuity | F27: A lump sum is paid in and income starts right away, usually within a year. | G27: A 67-year-old pays $200,000 and receives about $1,200 a month for life. | H27: Personal | J27: Life Insurance > Annuities > Immediate Annuity
A28: life.annuities.deferred | B28: life.annuities | C28: 3 | D28: Deferred Annuity | F28: Money grows for years before income starts. | G28: A 50-year-old invests now to start income at 65. | H28: Personal | I28: Withdrawals before age 59 1/2 usually face a 10% IRS penalty on earnings. | J28: Life Insurance > Annuities > Deferred Annuity
A29: life.annuities.deferred.fixed | B29: life.annuities.deferred | C29: 4 | D29: Fixed Annuity | E29: Multi-Year Guaranteed Annuity (MYGA) | F29: Earns a guaranteed fixed interest rate for a set period. | G29: A cautious saver locks in a 5% rate for 5 years. | H29: Personal | J29: Life Insurance > Annuities > Deferred Annuity > Fixed Annuity
A30: life.annuities.deferred.fia | B30: life.annuities.deferred | C30: 4 | D30: Fixed Indexed Annuity (FIA) | E30: Equity-indexed annuity | F30: Interest is linked to a market index with a cap and a zero floor, so principal isn't lost to market drops. | G30: A pre-retiree wants some index-linked growth with no loss of principal. | H30: Personal | I30: State-regulated insurance product, not a security. | J30: Life Insurance > Annuities > Deferred Annuity > Fixed Indexed Annuity (FIA)
A31: life.annuities.deferred.variable | B31: life.annuities.deferred | C31: 4 | D31: Variable Annuity | F31: Money is invested in sub-accounts, so value can rise or fall; optional riders can guarantee income or a death benefit. | G31: An investor holds funds inside a variable annuity with a lifetime income rider. | H31: Personal | I31: Sold with a prospectus; FINRA Rule 2330 governs suitability. | J31: Life Insurance > Annuities > Deferred Annuity > Variable Annuity
A32: life.annuities.deferred.variable.gmdb | B32: life.annuities.deferred.variable | C32: 5 | D32: Guaranteed Minimum Death Benefit (GMDB) | E32: Enhanced death benefit | F32: A variable annuity rider guaranteeing heirs receive at least a set amount (e.g. premiums paid or a high-water mark) even if investments fell. | G32: Markets drop 30% but the owner's heirs still get the full amount invested. | H32: Personal | J32: Life Insurance > Annuities > Deferred Annuity > Variable Annuity > Guaranteed Minimum Death Benefit (GMDB)
A33: life.annuities.deferred.variable.glwb | B33: life.annuities.deferred.variable | C33: 5 | D33: Guaranteed Lifetime Withdrawal Benefit (GLWB) | E33: GMWB; Lifetime income rider | F33: A rider that lets you withdraw a set percentage each year for life, even if the account value runs out. | G33: A retiree withdraws 5% of a $400,000 benefit base every year for life. | H33: Personal | I33: The most common living benefit rider on US variable and indexed annuities. | J33: Life Insurance > Annuities > Deferred Annuity > Variable Annuity > Guaranteed Lifetime Withdrawal Benefit (GLWB)
A34: life.annuities.deferred.variable.gmib | B34: life.annuities.deferred.variable | C34: 5 | D34: Guaranteed Minimum Income Benefit (GMIB) | F34: A rider guaranteeing a minimum level of lifetime income if the contract is annuitized after a waiting period. | G34: An owner annuitizes at 70 using a guaranteed income base. | H34: Personal | I34: Less widely sold today than GLWBs. | J34: Life Insurance > Annuities > Deferred Annuity > Variable Annuity > Guaranteed Minimum Income Benefit (GMIB)
A35: life.annuities.deferred.variable.gmab | B35: life.annuities.deferred.variable | C35: 5 | D35: Guaranteed Minimum Accumulation Benefit (GMAB) | F35: A rider guaranteeing the account will be worth at least a set amount after a waiting period, such as 10 years. | G35: After 10 years the account is topped up to the original premium. | H35: Personal | J35: Life Insurance > Annuities > Deferred Annuity > Variable Annuity > Guaranteed Minimum Accumulation Benefit (GMAB)
A36: life.annuities.deferred.rila | B36: life.annuities.deferred | C36: 4 | D36: Registered Index-Linked Annuity (RILA) | E36: Buffered annuity; Structured annuity | F36: Index-linked returns with a buffer or floor that limits (but does not remove) losses, in exchange for higher caps. | G36: A saver accepts losses beyond -10% in exchange for a higher upside cap. | H36: Personal | I36: SEC-registered; one of the fastest-growing US annuity categories since 2020. | J36: Life Insurance > Annuities > Deferred Annuity > Registered Index-Linked Annuity (RILA)
A37: life.annuities.deferred.qlac | B37: life.annuities.deferred | C37: 4 | D37: Qualified Longevity Annuity Contract (QLAC) | E37: Longevity annuity | F37: A deferred annuity bought with retirement account (e.g. IRA, 401(k)) money that can start paying as late as age 85. | G37: A retiree uses part of an IRA to guarantee income from age 85. | H37: Personal | I37: Premium limit set by IRS (indexed; $200,000 after SECURE 2.0). Excluded from required minimum distributions until payments start. | J37: Life Insurance > Annuities > Deferred Annuity > Qualified Longevity Annuity Contract (QLAC)
A38: life.annuities.joint | B38: life.annuities | C38: 3 | D38: Joint and Survivor Annuity | F38: Keeps paying income while either of two people is alive, sometimes at a reduced rate after the first dies. | G38: A married couple buys an annuity that pays until the second spouse dies. | H38: Personal | I38: ERISA requires this as the default form for married participants in many pension plans. | J38: Life Insurance > Annuities > Joint and Survivor Annuity
A39: life.annuities.structured_settlement | B39: life.annuities | C39: 3 | D39: Structured Settlement Annuity | F39: An annuity used to pay a lawsuit or injury settlement as a stream of payments instead of a lump sum. | G39: An injury victim receives monthly payments for 30 years from a settlement. | H39: Personal | I39: Payments for physical injury are generally tax-free under IRC Section 104. | J39: Life Insurance > Annuities > Structured Settlement Annuity
A40: life.annuities.pension_risk_transfer | B40: life.annuities | C40: 3 | D40: Pension Risk Transfer (Group Annuity) | E40: Pension buyout; Group annuity contract | F40: An employer pays an insurer to take over its pension obligations, and the insurer pays retirees' pensions. | G40: A manufacturer transfers its retirees' pensions to a life insurer. | H40: Commercial | I40: Governed by ERISA and Department of Labor Interpretive Bulletin 95-1 on selecting annuity providers. | J40: Life Insurance > Annuities > Pension Risk Transfer (Group Annuity)
A41: life.group_life | B41: life | C41: 2 | D41: Group Life & Employee Benefits | E41: Employee benefits | F41: Life and related covers bought by an employer for staff as part of a benefits package. | G41: A tech company offers life cover, disability cover and a retirement plan to all employees. | H41: Commercial | I41: Most employer benefit plans are governed by ERISA. | J41: Life Insurance > Group Life & Employee Benefits
A42: life.group_life.group_term | B42: life.group_life | C42: 3 | D42: Group Term Life | E42: Basic life | F42: Employer-paid life cover, usually a flat amount or a multiple of salary, lasting while the person is employed. | G42: An employee's family receives 2x salary if they die while employed. | H42: Commercial | I42: Employer-paid coverage above $50,000 creates taxable imputed income for the employee (IRC Section 79). | J42: Life Insurance > Group Life & Employee Benefits > Group Term Life
A43: life.group_life.supplemental | B43: life.group_life | C43: 3 | D43: Supplemental / Voluntary Life | E43: Optional life | F43: Extra life cover that employees can buy through work at group rates, paid via payroll. | G43: An employee adds $300,000 of extra cover beyond the free employer-paid amount. | H43: Both | J43: Life Insurance > Group Life & Employee Benefits > Supplemental / Voluntary Life
A44: life.group_life.dependent_life | B44: life.group_life | C44: 3 | D44: Dependent Life | E44: Spouse and child life | F44: Small group life coverage on an employee's spouse and children. | G44: An employee adds $20,000 of cover for their spouse. | H44: Both | J44: Life Insurance > Group Life & Employee Benefits > Dependent Life
A45: life.group_life.key_person | B45: life.group_life | C45: 3 | D45: Key Person Insurance | E45: Key man insurance | F45: A business insures the life of a vital employee or owner, and the business receives the payout. | G45: A startup insures its founder CTO so it can afford to replace her if she dies. | H45: Commercial | I45: Employer-owned policies must meet IRC Section 101(j) notice and consent rules for tax-free proceeds. | J45: Life Insurance > Group Life & Employee Benefits > Key Person Insurance
A46: life.group_life.buy_sell | B46: life.group_life | C46: 3 | D46: Buy-Sell Funding | E46: Cross-purchase; Entity redemption | F46: Life cover used to fund an agreement where surviving owners buy a deceased owner's share of the business. | G46: Two partners each insure the other so the survivor can buy out the family of the deceased. | H46: Commercial | J46: Life Insurance > Group Life & Employee Benefits > Buy-Sell Funding
A47: life.group_life.coli | B47: life.group_life | C47: 3 | D47: Corporate-Owned Life Insurance (COLI) | E47: Bank-owned life insurance (BOLI) | F47: Life policies owned by a company on employees, often used to fund executive benefit obligations. | G47: A bank owns policies on executives to help fund deferred compensation. | H47: Commercial | J47: Life Insurance > Group Life & Employee Benefits > Corporate-Owned Life Insurance (COLI)
A48: life.group_life.split_dollar | B48: life.group_life | C48: 3 | D48: Split-Dollar Life | F48: An arrangement where an employer and employee share the cost and benefits of a permanent life policy. | G48: A company pays premiums on an executive's policy and recovers them at death. | H48: Commercial | I48: Taxed under IRS split-dollar regulations (2003). | J48: Life Insurance > Group Life & Employee Benefits > Split-Dollar Life
A49: life.life_riders | B49: life | C49: 2 | D49: Life Insurance Riders | E49: Add-ons; Optional benefits | F49: Optional extras added to a life policy, often for an extra premium. | G49: A buyer adds a waiver of premium rider to a term policy. | H49: Personal | J49: Life Insurance > Life Insurance Riders
A50: life.life_riders.adb | B50: life.life_riders | C50: 3 | D50: Accidental Death Benefit Rider | E50: Double indemnity | F50: Pays an extra amount if death is caused by an accident. | G50: A policy pays double the face amount after a fatal car crash. | H50: Personal | J50: Life Insurance > Life Insurance Riders > Accidental Death Benefit Rider
A51: life.life_riders.wop | B51: life.life_riders | C51: 3 | D51: Waiver of Premium Rider | F51: Stops premiums being due if the policyholder becomes totally disabled, keeping the cover in force. | G51: After a disabling stroke, the insured's policy stays active without further payments. | H51: Personal | J51: Life Insurance > Life Insurance Riders > Waiver of Premium Rider
A52: life.life_riders.abr | B52: life.life_riders | C52: 3 | D52: Accelerated Death Benefit Rider | E52: Living benefits rider | F52: Lets a terminally, chronically or critically ill insured receive part of the death benefit while still alive. | G52: A patient given 6 months to live gets an advance on their policy to pay for care. | H52: Personal | I52: Terminal illness acceleration is generally tax-free under the HIPAA 1996 rules. | J52: Life Insurance > Life Insurance Riders > Accelerated Death Benefit Rider
A53: life.life_riders.abr.terminal | B53: life.life_riders.abr | C53: 4 | D53: Terminal Illness Rider | F53: Pays part of the death benefit early if life expectancy is 12 or 24 months or less. | G53: A cancer patient receives 75% of the benefit early. | H53: Personal | J53: Life Insurance > Life Insurance Riders > Accelerated Death Benefit Rider > Terminal Illness Rider
A54: life.life_riders.abr.chronic | B54: life.life_riders.abr | C54: 4 | D54: Chronic Illness Rider | F54: Pays part of the death benefit early if you can't perform 2 of 6 activities of daily living. | G54: A policyholder unable to bathe or dress unaided receives monthly payments. | H54: Personal | J54: Life Insurance > Life Insurance Riders > Accelerated Death Benefit Rider > Chronic Illness Rider
A55: life.life_riders.abr.critical | B55: life.life_riders.abr | C55: 4 | D55: Critical Illness Rider | F55: Pays part of the death benefit early on diagnosis of a listed condition such as heart attack or stroke. | G55: A policyholder draws $50,000 after a heart attack. | H55: Personal | J55: Life Insurance > Life Insurance Riders > Accelerated Death Benefit Rider > Critical Illness Rider
A56: life.life_riders.ltc_rider | B56: life.life_riders | C56: 3 | D56: Long-Term Care Rider | F56: Lets the death benefit be used to pay for long-term care costs, meeting federal tax-qualified LTC rules. | G56: An insured with dementia uses part of the death benefit to pay for memory care. | H56: Personal | I56: Tax-qualified under IRC Section 7702B when it meets federal standards. | J56: Life Insurance > Life Insurance Riders > Long-Term Care Rider
A57: life.life_riders.child_rider | B57: life.life_riders | C57: 3 | D57: Child Term Rider | E57: Children's term | F57: Adds small term cover for the policyholder's children. | G57: A parent adds $10,000 of cover for all children on their own policy. | H57: Personal | J57: Life Insurance > Life Insurance Riders > Child Term Rider
A58: life.life_riders.gir | B58: life.life_riders | C58: 3 | D58: Guaranteed Insurability Rider | E58: Guaranteed purchase option | F58: Lets you buy more cover at set times or life events without new medical checks. | G58: A policyholder increases cover after the birth of a child without a medical exam. | H58: Personal | J58: Life Insurance > Life Insurance Riders > Guaranteed Insurability Rider
A59: life.life_riders.pua | B59: life.life_riders | C59: 3 | D59: Paid-Up Additions Rider | E59: PUA rider | F59: Lets you pay extra premium into a whole life policy to buy small amounts of fully paid-up cover, boosting cash value. | G59: A policyholder adds $5,000 a year of PUAs to grow cash value faster. | H59: Personal | I59: Must be managed to avoid MEC status. | J59: Life Insurance > Life Insurance Riders > Paid-Up Additions Rider
A60: health | C60: 1 | D60: Health Insurance | E60: Medical insurance; Health coverage | F60: Pays for medical care, or pays cash, when you are ill, injured or disabled. | G60: A family's plan pays most of the hospital bill when a child needs surgery. | H60: Both | I60: Private plans are regulated by states and by federal law (ACA, ERISA, HIPAA). Government programs are listed under Social & Government Programs. | J60: Health Insurance
A61: health.major_medical | B61: health | C61: 2 | D61: Major Medical (Comprehensive) | E61: Health plan | F61: Comprehensive health cover for doctor visits, hospital stays, prescriptions and preventive care, bought individually or through an employer. | G61: A freelancer buys an individual plan on the marketplace. | H61: Both | I61: Under the ACA, major medical plans must cover 10 essential health benefits, can't deny pre-existing conditions, and have annual out-of-pocket maximums. | J61: Health Insurance > Major Medical (Comprehensive)
A62: health.major_medical.plan_types | B62: health.major_medical | C62: 3 | D62: Network Plan Types | E62: Managed care plans | F62: Plan designs that control cost through provider networks and rules on referrals. | G62: An employee chooses between an HMO and a PPO during open enrollment. | H62: Both | J62: Health Insurance > Major Medical (Comprehensive) > Network Plan Types
A63: health.major_medical.plan_types.hmo | B63: health.major_medical.plan_types | C63: 4 | D63: Health Maintenance Organization (HMO) | F63: You must use the plan's network and usually need a referral from your primary care physician (PCP) to see a specialist; out-of-network care is not covered except emergencies. | G63: A family accepts a narrow network for lower premiums. | H63: Both | I63: Licensed under state HMO laws; example: Kaiser Permanente. | J63: Health Insurance > Major Medical (Comprehensive) > Network Plan Types > Health Maintenance Organization (HMO)
A64: health.major_medical.plan_types.ppo | B64: health.major_medical.plan_types | C64: 4 | D64: Preferred Provider Organization (PPO) | F64: You can see any doctor without referrals; in-network care costs less, and out-of-network care is partly covered. | G64: A person who travels a lot picks a PPO to see specialists anywhere. | H64: Both | I64: The most common plan type in employer coverage. | J64: Health Insurance > Major Medical (Comprehensive) > Network Plan Types > Preferred Provider Organization (PPO)
A65: health.major_medical.plan_types.epo | B65: health.major_medical.plan_types | C65: 4 | D65: Exclusive Provider Organization (EPO) | F65: Like a PPO with no referrals, but only in-network care is covered (except emergencies). | G65: A worker happy with the local network picks an EPO to save money. | H65: Both | J65: Health Insurance > Major Medical (Comprehensive) > Network Plan Types > Exclusive Provider Organization (EPO)
A66: health.major_medical.plan_types.pos | B66: health.major_medical.plan_types | C66: 4 | D66: Point of Service (POS) | F66: A hybrid: you choose a PCP and need referrals like an HMO, but can go out of network at higher cost like a PPO. | G66: A family wants a gatekeeper doctor with some out-of-network flexibility. | H66: Both | J66: Health Insurance > Major Medical (Comprehensive) > Network Plan Types > Point of Service (POS)
A67: health.major_medical.plan_types.hdhp | B67: health.major_medical.plan_types | C67: 4 | D67: High Deductible Health Plan (HDHP) | E67: HSA-eligible plan; Consumer-directed health plan | F67: A plan with a high deductible and lower premium; it can be paired with a tax-advantaged Health Savings Account (HSA). | G67: A healthy 28-year-old picks an HDHP and saves the premium difference in an HSA. | H67: Both | I67: The IRS sets minimum deductibles and maximum out-of-pocket limits yearly for HSA eligibility. | J67: Health Insurance > Major Medical (Comprehensive) > Network Plan Types > High Deductible Health Plan (HDHP)
A68: health.major_medical.plan_types.indemnity | B68: health.major_medical.plan_types | C68: 4 | D68: Fee-for-Service Indemnity Plan | E68: Traditional indemnity | F68: Pays a share of any provider's bills with no network; now rare and expensive. | G68: A patient sees any doctor and is reimbursed 80% after the deductible. | H68: Both | J68: Health Insurance > Major Medical (Comprehensive) > Network Plan Types > Fee-for-Service Indemnity Plan
A69: health.major_medical.individual_market | B69: health.major_medical | C69: 3 | D69: Individual Market Plans | E69: Marketplace plans; Obamacare plans | F69: Health plans people buy for themselves, on or off the government exchanges. | G69: A self-employed person compares plans on HealthCare.gov and qualifies for a subsidy. | H69: Personal | I69: Sold on HealthCare.gov or a state-run exchange (e.g. Covered California). Premium tax credits available on-exchange by income. Open enrollment runs each fall. | J69: Health Insurance > Major Medical (Comprehensive) > Individual Market Plans
A70: health.major_medical.individual_market.bronze | B70: health.major_medical.individual_market | C70: 4 | D70: Bronze Plan | F70: Covers about 60% of average costs: lowest premium, highest out-of-pocket. | G70: A young healthy person wants protection mostly against large bills. | H70: Personal | I70: Actuarial value approx. 60%. | J70: Health Insurance > Major Medical (Comprehensive) > Individual Market Plans > Bronze Plan
A71: health.major_medical.individual_market.silver | B71: health.major_medical.individual_market | C71: 4 | D71: Silver Plan | F71: Covers about 70% of average costs; the only tier eligible for extra cost-sharing reductions for lower incomes. | G71: A low-income household picks silver to get reduced deductibles. | H71: Personal | I71: The second-lowest-cost silver plan is the benchmark for subsidies. | J71: Health Insurance > Major Medical (Comprehensive) > Individual Market Plans > Silver Plan
A72: health.major_medical.individual_market.silver.csr_73 | B72: health.major_medical.individual_market.silver | C72: 5 | D72: Silver 73% CSR Variant | E72: Enhanced silver 73 | F72: A silver plan version with lower deductibles and copays (about 73% actuarial value) for enrollees with incomes of 200-250% of the federal poverty level. | G72: A household at 220% of poverty gets a lower deductible automatically. | H72: Personal | I72: Cost-sharing reductions are available only on-exchange with a silver plan. | J72: Health Insurance > Major Medical (Comprehensive) > Individual Market Plans > Silver Plan > Silver 73% CSR Variant
A73: health.major_medical.individual_market.silver.csr_87 | B73: health.major_medical.individual_market.silver | C73: 5 | D73: Silver 87% CSR Variant | E73: Enhanced silver 87 | F73: A silver plan version with about 87% actuarial value for incomes of 150-200% of the federal poverty level. | G73: A single adult at 175% of poverty pays a much lower deductible. | H73: Personal | J73: Health Insurance > Major Medical (Comprehensive) > Individual Market Plans > Silver Plan > Silver 87% CSR Variant
A74: health.major_medical.individual_market.silver.csr_94 | B74: health.major_medical.individual_market.silver | C74: 5 | D74: Silver 94% CSR Variant | E74: Enhanced silver 94 | F74: A silver plan version with about 94% actuarial value for incomes of 100-150% of the federal poverty level. | G74: A low-income worker gets near-platinum cost sharing at a silver price. | H74: Personal | J74: Health Insurance > Major Medical (Comprehensive) > Individual Market Plans > Silver Plan > Silver 94% CSR Variant
A75: health.major_medical.individual_market.gold | B75: health.major_medical.individual_market | C75: 4 | D75: Gold Plan | F75: Covers about 80% of average costs: higher premium, lower out-of-pocket. | G75: Someone with regular prescriptions picks gold. | H75: Personal | I75: Actuarial value approx. 80%. | J75: Health Insurance > Major Medical (Comprehensive) > Individual Market Plans > Gold Plan
A76: health.major_medical.individual_market.platinum | B76: health.major_medical.individual_market | C76: 4 | D76: Platinum Plan | F76: Covers about 90% of average costs: highest premium, lowest out-of-pocket. | G76: A person expecting major surgery chooses platinum. | H76: Personal | I76: Not offered in every state. | J76: Health Insurance > Major Medical (Comprehensive) > Individual Market Plans > Platinum Plan
A77: health.major_medical.individual_market.catastrophic | B77: health.major_medical.individual_market | C77: 4 | D77: Catastrophic Plan | F77: Very high deductible plan for people under 30 or with a hardship exemption; covers preventive care and 3 primary care visits before the deductible. | G77: A 25-year-old buys a catastrophic plan as a safety net. | H77: Personal | I77: Not eligible for premium tax credits. | J77: Health Insurance > Major Medical (Comprehensive) > Individual Market Plans > Catastrophic Plan
A78: health.major_medical.group_health | B78: health.major_medical | C78: 3 | D78: Employer Group Health | E78: Employer-sponsored insurance (ESI) | F78: Health cover an employer offers to employees and their families, usually sharing the premium cost. | G78: A company covers employees and their dependents under one plan. | H78: Commercial | I78: The largest source of US health coverage. Employers with 50+ full-time employees face the ACA employer mandate. | J78: Health Insurance > Major Medical (Comprehensive) > Employer Group Health
A79: health.major_medical.group_health.fully_insured | B79: health.major_medical.group_health | C79: 4 | D79: Fully Insured Plan | F79: The employer pays premiums and the insurer carries the claims risk. | G79: A 50-person firm buys a standard group plan from an insurer. | H79: Commercial | I79: Subject to state insurance mandates. | J79: Health Insurance > Major Medical (Comprehensive) > Employer Group Health > Fully Insured Plan
A80: health.major_medical.group_health.self_funded | B80: health.major_medical.group_health | C80: 4 | D80: Self-Funded (ASO) Plan | E80: Self-insured plan; Administrative Services Only | F80: The employer pays claims from its own funds and hires an insurer or third-party administrator (TPA) only to process them. | G80: A large retailer self-funds health claims to control costs. | H80: Commercial | I80: Governed by federal ERISA, which preempts most state insurance mandates. | J80: Health Insurance > Major Medical (Comprehensive) > Employer Group Health > Self-Funded (ASO) Plan
A81: health.major_medical.group_health.stop_loss | B81: health.major_medical.group_health | C81: 4 | D81: Medical Stop-Loss | E81: Excess risk insurance | F81: Protects a self-funded employer against very large individual claims (specific) or high total claims (aggregate). | G81: A self-funded employer is reimbursed for an employee's $1 million cancer treatment above a $150,000 deductible. | H81: Commercial | I81: Regulated by states as insurance to the employer, not as health insurance. | J81: Health Insurance > Major Medical (Comprehensive) > Employer Group Health > Medical Stop-Loss
A82: health.major_medical.group_health.level_funded | B82: health.major_medical.group_health | C82: 4 | D82: Level-Funded Plan | F82: A small-business form of self-funding with fixed monthly payments that include stop-loss cover and possible year-end refunds. | G82: A 40-person company gets a refund when claims are lower than expected. | H82: Commercial | J82: Health Insurance > Major Medical (Comprehensive) > Employer Group Health > Level-Funded Plan
A83: health.major_medical.group_health.ichra | B83: health.major_medical.group_health | C83: 4 | D83: Individual Coverage HRA (ICHRA) | F83: The employer gives tax-free money that employees use to buy their own individual-market plans. | G83: A startup gives each employee $500 a month to buy a marketplace plan. | H83: Commercial | I83: Created by federal rule in 2020. | J83: Health Insurance > Major Medical (Comprehensive) > Employer Group Health > Individual Coverage HRA (ICHRA)
A84: health.major_medical.group_health.cobra | B84: health.major_medical.group_health | C84: 4 | D84: COBRA Continuation Coverage | F84: Lets employees and families keep their employer group plan for a limited time (usually 18 months) after leaving a job, paying the full premium. | G84: A laid-off worker keeps the family on the group plan for 18 months. | H84: Personal | I84: Federal law for employers with 20+ employees; many states have "mini-COBRA" laws for smaller employers. | J84: Health Insurance > Major Medical (Comprehensive) > Employer Group Health > COBRA Continuation Coverage
A85: health.major_medical.short_term | B85: health.major_medical | C85: 3 | D85: Short-Term Limited-Duration Insurance (STLDI) | E85: Short-term health | F85: Temporary health cover that doesn't have to follow ACA rules, so it can exclude pre-existing conditions. | G85: Someone between jobs buys a 3-month plan. | H85: Personal | I85: Federal duration limits have changed several times (2018 and 2024 rules; check current federal status). Some states restrict or ban it outright. | J85: Health Insurance > Major Medical (Comprehensive) > Short-Term Limited-Duration Insurance (STLDI)
A86: health.major_medical.health_sharing | B86: health.major_medical | C86: 3 | D86: Health Care Sharing Ministries | E86: Health sharing plans | F86: Members of a faith-based group share each other's medical bills; this is not insurance and has no guarantee of payment. | G86: A family joins a sharing ministry and submits bills to be shared by members. | H86: Personal | I86: Not regulated as insurance in most states; exempt from ACA rules. | J86: Health Insurance > Major Medical (Comprehensive) > Health Care Sharing Ministries
A87: health.medicare_private | B87: health | C87: 2 | D87: Private Medicare Plans | E87: Medicare private options | F87: Private insurance products that work with or replace federal Medicare benefits. | G87: A 65-year-old chooses between Medigap and a Medicare Advantage plan. | H87: Personal | I87: Regulated by CMS (federal) plus state insurance departments for Medigap. Original Medicare itself is under Social & Government Programs. | J87: Health Insurance > Private Medicare Plans
A88: health.medicare_private.medicare_advantage | B88: health.medicare_private | C88: 3 | D88: Medicare Advantage (Part C) | E88: MA plan | F88: A private plan that replaces Original Medicare, often as an HMO or PPO, usually including drug coverage and extras like dental and vision. | G88: A retiree picks a $0-premium HMO Medicare Advantage plan with dental. | H88: Personal | I88: Now covers roughly half of Medicare beneficiaries. Annual enrollment Oct 15-Dec 7. | J88: Health Insurance > Private Medicare Plans > Medicare Advantage (Part C)
A89: health.medicare_private.medicare_advantage.ma_hmo | B89: health.medicare_private.medicare_advantage | C89: 4 | D89: Medicare Advantage HMO | F89: A Medicare Advantage plan with a network and referrals. | G89: A retiree uses doctors in the plan's local network. | H89: Personal | J89: Health Insurance > Private Medicare Plans > Medicare Advantage (Part C) > Medicare Advantage HMO
A90: health.medicare_private.medicare_advantage.ma_ppo | B90: health.medicare_private.medicare_advantage | C90: 4 | D90: Medicare Advantage PPO | F90: A Medicare Advantage plan that also partly covers out-of-network care. | G90: A retiree who spends winters in another state picks a PPO. | H90: Personal | J90: Health Insurance > Private Medicare Plans > Medicare Advantage (Part C) > Medicare Advantage PPO
A91: health.medicare_private.medicare_advantage.snp | B91: health.medicare_private.medicare_advantage | C91: 4 | D91: Special Needs Plan (SNP) | F91: A Medicare Advantage plan for people who are also on Medicaid (D-SNP), have certain chronic conditions (C-SNP) or live in institutions (I-SNP). | G91: A low-income senior on both Medicare and Medicaid joins a D-SNP. | H91: Personal | J91: Health Insurance > Private Medicare Plans > Medicare Advantage (Part C) > Special Needs Plan (SNP)
A92: health.medicare_private.medicare_advantage.snp.d_snp | B92: health.medicare_private.medicare_advantage.snp | C92: 5 | D92: Dual Eligible SNP (D-SNP) | F92: For people who have both Medicare and Medicaid; coordinates benefits of the two programs. | G92: A low-income senior gets Medicare and Medicaid benefits through one plan. | H92: Personal | I92: The largest SNP type. | J92: Health Insurance > Private Medicare Plans > Medicare Advantage (Part C) > Special Needs Plan (SNP) > Dual Eligible SNP (D-SNP)
A93: health.medicare_private.medicare_advantage.snp.c_snp | B93: health.medicare_private.medicare_advantage.snp | C93: 5 | D93: Chronic Condition SNP (C-SNP) | F93: For people with specific severe chronic conditions such as diabetes, heart failure or ESRD. | G93: A retiree with heart failure joins a plan with specialised care coordination. | H93: Personal | J93: Health Insurance > Private Medicare Plans > Medicare Advantage (Part C) > Special Needs Plan (SNP) > Chronic Condition SNP (C-SNP)
A94: health.medicare_private.medicare_advantage.snp.i_snp | B94: health.medicare_private.medicare_advantage.snp | C94: 5 | D94: Institutional SNP (I-SNP) | F94: For people who live in nursing homes or need that level of care at home. | G94: A nursing home resident's plan provides on-site care teams. | H94: Personal | J94: Health Insurance > Private Medicare Plans > Medicare Advantage (Part C) > Special Needs Plan (SNP) > Institutional SNP (I-SNP)
A95: health.medicare_private.medicare_advantage.pffs | B95: health.medicare_private.medicare_advantage | C95: 4 | D95: Private Fee-for-Service (PFFS) | F95: A Medicare Advantage plan that sets its own payment terms with any provider willing to accept them. | G95: Rare today; available in a few rural areas. | H95: Personal | J95: Health Insurance > Private Medicare Plans > Medicare Advantage (Part C) > Private Fee-for-Service (PFFS)
A96: health.medicare_private.medicare_advantage.msa | B96: health.medicare_private.medicare_advantage | C96: 4 | D96: Medicare Medical Savings Account (MSA) | F96: A high-deductible Medicare Advantage plan paired with a savings account funded by Medicare. | G96: A healthy retiree uses the deposit toward costs before the deductible. | H96: Personal | I96: Limited availability. | J96: Health Insurance > Private Medicare Plans > Medicare Advantage (Part C) > Medicare Medical Savings Account (MSA)
A97: health.medicare_private.part_d | B97: health.medicare_private | C97: 3 | D97: Medicare Part D (Prescription Drug Plan) | E97: PDP | F97: Standalone private plans that cover prescription drugs for people on Original Medicare. | G97: A retiree with Original Medicare adds a Part D plan for their medications. | H97: Personal | I97: Inflation Reduction Act capped Part D out-of-pocket spending at $2,000 in 2025 (indexed after). | J97: Health Insurance > Private Medicare Plans > Medicare Part D (Prescription Drug Plan)
A98: health.medicare_private.medigap | B98: health.medicare_private | C98: 3 | D98: Medicare Supplement (Medigap) | E98: Med Supp | F98: Private policies that pay gaps in Original Medicare, such as deductibles and 20% coinsurance, sold as standardized plans lettered A-N. | G98: A 66-year-old buys Medigap Plan G to limit out-of-pocket costs. | H98: Personal | I98: Plans standardized by federal law; Massachusetts, Minnesota and Wisconsin use their own designs. | J98: Health Insurance > Private Medicare Plans > Medicare Supplement (Medigap)
A99: health.medicare_private.medigap.plan_g | B99: health.medicare_private.medigap | C99: 4 | D99: Medigap Plan G | F99: Covers almost all gaps except the Part B deductible; the most popular plan for new enrollees. | G99: A new retiree picks Plan G for predictable costs. | H99: Personal | J99: Health Insurance > Private Medicare Plans > Medicare Supplement (Medigap) > Medigap Plan G
A100: health.medicare_private.medigap.plan_n | B100: health.medicare_private.medigap | C100: 4 | D100: Medigap Plan N | F100: Lower premium than G, with small copays for office and ER visits. | G100: A retiree who rarely sees a doctor picks Plan N. | H100: Personal | J100: Health Insurance > Private Medicare Plans > Medicare Supplement (Medigap) > Medigap Plan N
...

Sheet Outline
A1: Level 1 | B1: Level 2 | C1: Level 3 | D1: Level 4 | E1: Level 5 | F1: ID
A2: Life Insurance | F2: life
B3: Term Life | F3: life.term
C4: Level Term | F4: life.term.level
C5: Decreasing Term | F5: life.term.decreasing
C6: Annually Renewable Term (ART) | F6: life.term.art
C7: Convertible Term | F7: life.term.convertible
C8: Return of Premium Term (ROP) | F8: life.term.rop
C9: Credit Life Insurance | F9: life.term.credit_life
B10: Permanent Life | F10: life.permanent
C11: Whole Life | F11: life.permanent.whole
D12: Participating Whole Life | F12: life.permanent.whole.participating
D13: Non-Participating Whole Life | F13: life.permanent.whole.non_participating
D14: Limited Pay Whole Life | F14: life.permanent.whole.limited_pay
D15: Single Premium Whole Life (SPWL) | F15: life.permanent.whole.single_premium
D16: Final Expense Insurance | F16: life.permanent.whole.final_expense
D17: Guaranteed Issue Whole Life | F17: life.permanent.whole.guaranteed_issue
D18: Industrial / Home Service Life | F18: life.permanent.whole.industrial
C19: Universal Life (UL) | F19: life.permanent.universal
D20: Current Assumption Universal Life | F20: life.permanent.universal.current_assumption
D21: Guaranteed Universal Life (GUL) | F21: life.permanent.universal.gul
D22: Indexed Universal Life (IUL) | F22: life.permanent.universal.iul
D23: Variable Universal Life (VUL) | F23: life.permanent.universal.vul
D24: Survivorship Universal Life | F24: life.permanent.universal.survivorship
C25: Variable Life | F25: life.permanent.variable_life
B26: Annuities | F26: life.annuities
C27: Immediate Annuity | F27: life.annuities.immediate
C28: Deferred Annuity | F28: life.annuities.deferred
D29: Fixed Annuity | F29: life.annuities.deferred.fixed
D30: Fixed Indexed Annuity (FIA) | F30: life.annuities.deferred.fia
D31: Variable Annuity | F31: life.annuities.deferred.variable
E32: Guaranteed Minimum Death Benefit (GMDB) | F32: life.annuities.deferred.variable.gmdb
E33: Guaranteed Lifetime Withdrawal Benefit (GLWB) | F33: life.annuities.deferred.variable.glwb
E34: Guaranteed Minimum Income Benefit (GMIB) | F34: life.annuities.deferred.variable.gmib
E35: Guaranteed Minimum Accumulation Benefit (GMAB) | F35: life.annuities.deferred.variable.gmab
D36: Registered Index-Linked Annuity (RILA) | F36: life.annuities.deferred.rila
D37: Qualified Longevity Annuity Contract (QLAC) | F37: life.annuities.deferred.qlac
C38: Joint and Survivor Annuity | F38: life.annuities.joint
C39: Structured Settlement Annuity | F39: life.annuities.structured_settlement
C40: Pension Risk Transfer (Group Annuity) | F40: life.annuities.pension_risk_transfer
B41: Group Life & Employee Benefits | F41: life.group_life
C42: Group Term Life | F42: life.group_life.group_term
C43: Supplemental / Voluntary Life | F43: life.group_life.supplemental
C44: Dependent Life | F44: life.group_life.dependent_life
C45: Key Person Insurance | F45: life.group_life.key_person
C46: Buy-Sell Funding | F46: life.group_life.buy_sell
C47: Corporate-Owned Life Insurance (COLI) | F47: life.group_life.coli
C48: Split-Dollar Life | F48: life.group_life.split_dollar
B49: Life Insurance Riders | F49: life.life_riders
C50: Accidental Death Benefit Rider | F50: life.life_riders.adb
C51: Waiver of Premium Rider | F51: life.life_riders.wop
C52: Accelerated Death Benefit Rider | F52: life.life_riders.abr
D53: Terminal Illness Rider | F53: life.life_riders.abr.terminal
D54: Chronic Illness Rider | F54: life.life_riders.abr.chronic
D55: Critical Illness Rider | F55: life.life_riders.abr.critical
C56: Long-Term Care Rider | F56: life.life_riders.ltc_rider
C57: Child Term Rider | F57: life.life_riders.child_rider
C58: Guaranteed Insurability Rider | F58: life.life_riders.gir
C59: Paid-Up Additions Rider | F59: life.life_riders.pua
A60: Health Insurance | F60: health
B61: Major Medical (Comprehensive) | F61: health.major_medical
C62: Network Plan Types | F62: health.major_medical.plan_types
D63: Health Maintenance Organization (HMO) | F63: health.major_medical.plan_types.hmo
D64: Preferred Provider Organization (PPO) | F64: health.major_medical.plan_types.ppo
D65: Exclusive Provider Organization (EPO) | F65: health.major_medical.plan_types.epo
D66: Point of Service (POS) | F66: health.major_medical.plan_types.pos
D67: High Deductible Health Plan (HDHP) | F67: health.major_medical.plan_types.hdhp
D68: Fee-for-Service Indemnity Plan | F68: health.major_medical.plan_types.indemnity
C69: Individual Market Plans | F69: health.major_medical.individual_market
D70: Bronze Plan | F70: health.major_medical.individual_market.bronze
D71: Silver Plan | F71: health.major_medical.individual_market.silver
E72: Silver 73% CSR Variant | F72: health.major_medical.individual_market.silver.csr_73
E73: Silver 87% CSR Variant | F73: health.major_medical.individual_market.silver.csr_87
E74: Silver 94% CSR Variant | F74: health.major_medical.individual_market.silver.csr_94
D75: Gold Plan | F75: health.major_medical.individual_market.gold
D76: Platinum Plan | F76: health.major_medical.individual_market.platinum
D77: Catastrophic Plan | F77: health.major_medical.individual_market.catastrophic
C78: Employer Group Health | F78: health.major_medical.group_health
D79: Fully Insured Plan | F79: health.major_medical.group_health.fully_insured
D80: Self-Funded (ASO) Plan | F80: health.major_medical.group_health.self_funded
D81: Medical Stop-Loss | F81: health.major_medical.group_health.stop_loss
D82: Level-Funded Plan | F82: health.major_medical.group_health.level_funded
D83: Individual Coverage HRA (ICHRA) | F83: health.major_medical.group_health.ichra
D84: COBRA Continuation Coverage | F84: health.major_medical.group_health.cobra
C85: Short-Term Limited-Duration Insurance (STLDI) | F85: health.major_medical.short_term
C86: Health Care Sharing Ministries | F86: health.major_medical.health_sharing
B87: Private Medicare Plans | F87: health.medicare_private
C88: Medicare Advantage (Part C) | F88: health.medicare_private.medicare_advantage
D89: Medicare Advantage HMO | F89: health.medicare_private.medicare_advantage.ma_hmo
D90: Medicare Advantage PPO | F90: health.medicare_private.medicare_advantage.ma_ppo
D91: Special Needs Plan (SNP) | F91: health.medicare_private.medicare_advantage.snp
E92: Dual Eligible SNP (D-SNP) | F92: health.medicare_private.medicare_advantage.snp.d_snp
E93: Chronic Condition SNP (C-SNP) | F93: health.medicare_private.medicare_advantage.snp.c_snp
E94: Institutional SNP (I-SNP) | F94: health.medicare_private.medicare_advantage.snp.i_snp
D95: Private Fee-for-Service (PFFS) | F95: health.medicare_private.medicare_advantage.pffs
D96: Medicare Medical Savings Account (MSA) | F96: health.medicare_private.medicare_advantage.msa
C97: Medicare Part D (Prescription Drug Plan) | F97: health.medicare_private.part_d
C98: Medicare Supplement (Medigap) | F98: health.medicare_private.medigap
D99: Medigap Plan G | F99: health.medicare_private.medigap.plan_g
D100: Medigap Plan N | F100: health.medicare_private.medigap.plan_n
...

Sheet Summary
A1: Insurance Taxonomy (US) - Summary
A3: Root category | B3: Root ID | C3: Nodes (incl. root) | D3: Max depth
A4: Life Insurance | B4: life | C4: =COUNTIF(Tree!$A:$A,B4)+COUNTIF(Tree!$A:$A,B4&".*") -> 58 | D4: =MAX(1,_xlfn.MAXIFS(Tree!$C:$C,Tree!$A:$A,B4&".*")) -> 5
A5: Health Insurance | B5: health | C5: =COUNTIF(Tree!$A:$A,B5)+COUNTIF(Tree!$A:$A,B5&".*") -> 69 | D5: =MAX(1,_xlfn.MAXIFS(Tree!$C:$C,Tree!$A:$A,B5&".*")) -> 5
A6: Personal Property Insurance | B6: property | C6: =COUNTIF(Tree!$A:$A,B6)+COUNTIF(Tree!$A:$A,B6&".*") -> 39 | D6: =MAX(1,_xlfn.MAXIFS(Tree!$C:$C,Tree!$A:$A,B6&".*")) -> 4
A7: Casualty & Liability Insurance | B7: casualty | C7: =COUNTIF(Tree!$A:$A,B7)+COUNTIF(Tree!$A:$A,B7&".*") -> 43 | D7: =MAX(1,_xlfn.MAXIFS(Tree!$C:$C,Tree!$A:$A,B7&".*")) -> 4
A8: Auto Insurance | B8: auto | C8: =COUNTIF(Tree!$A:$A,B8)+COUNTIF(Tree!$A:$A,B8&".*") -> 45 | D8: =MAX(1,_xlfn.MAXIFS(Tree!$C:$C,Tree!$A:$A,B8&".*")) -> 4
A9: Commercial Lines (Business Property & Packages) | B9: commercial | C9: =COUNTIF(Tree!$A:$A,B9)+COUNTIF(Tree!$A:$A,B9&".*") -> 29 | D9: =MAX(1,_xlfn.MAXIFS(Tree!$C:$C,Tree!$A:$A,B9&".*")) -> 4
A10: Marine, Aviation & Transit | B10: marine | C10: =COUNTIF(Tree!$A:$A,B10)+COUNTIF(Tree!$A:$A,B10&".*") -> 44 | D10: =MAX(1,_xlfn.MAXIFS(Tree!$C:$C,Tree!$A:$A,B10&".*")) -> 4
A11: Specialty Insurance | B11: specialty | C11: =COUNTIF(Tree!$A:$A,B11)+COUNTIF(Tree!$A:$A,B11&".*") -> 72 | D11: =MAX(1,_xlfn.MAXIFS(Tree!$C:$C,Tree!$A:$A,B11&".*")) -> 4
A12: Financial Lines | B12: financial | C12: =COUNTIF(Tree!$A:$A,B12)+COUNTIF(Tree!$A:$A,B12&".*") -> 44 | D12: =MAX(1,_xlfn.MAXIFS(Tree!$C:$C,Tree!$A:$A,B12&".*")) -> 4
A13: Agricultural & Crop Insurance | B13: agriculture | C13: =COUNTIF(Tree!$A:$A,B13)+COUNTIF(Tree!$A:$A,B13&".*") -> 25 | D13: =MAX(1,_xlfn.MAXIFS(Tree!$C:$C,Tree!$A:$A,B13&".*")) -> 4
A14: Social & Government Programs | B14: social | C14: =COUNTIF(Tree!$A:$A,B14)+COUNTIF(Tree!$A:$A,B14&".*") -> 36 | D14: =MAX(1,_xlfn.MAXIFS(Tree!$C:$C,Tree!$A:$A,B14&".*")) -> 3
A15: Reinsurance | B15: reinsurance | C15: =COUNTIF(Tree!$A:$A,B15)+COUNTIF(Tree!$A:$A,B15&".*") -> 20 | D15: =MAX(1,_xlfn.MAXIFS(Tree!$C:$C,Tree!$A:$A,B15&".*")) -> 4
A16: Alternative Risk Transfer (ART) | B16: art | C16: =COUNTIF(Tree!$A:$A,B16)+COUNTIF(Tree!$A:$A,B16&".*") -> 27 | D16: =MAX(1,_xlfn.MAXIFS(Tree!$C:$C,Tree!$A:$A,B16&".*")) -> 4
A17: Total | C17: =SUM(C4:C16) -> 551 | D17: =MAX(D4:D16) -> 5
A18: Check: rows in Tree sheet | C18: =COUNTA(Tree!$A:$A)-1 -> 551
A20: Level | C20: Nodes at level
A21: 1 | C21: =COUNTIF(Tree!$C:$C,A21) -> 13
A22: 2 | C22: =COUNTIF(Tree!$C:$C,A22) -> 87
A23: 3 | C23: =COUNTIF(Tree!$C:$C,A23) -> 295
A24: 4 | C24: =COUNTIF(Tree!$C:$C,A24) -> 146
A25: 5 | C25: =COUNTIF(Tree!$C:$C,A25) -> 10
A26: Total | C26: =SUM(C21:C25) -> 551
A28: By market
A29: Personal | C29: =COUNTIF(Tree!$H:$H,A29) -> 223
A30: Commercial | C30: =COUNTIF(Tree!$H:$H,A30) -> 270
A31: Both | C31: =COUNTIF(Tree!$H:$H,A31) -> 58
A33: Approach and sources
A34: Scope: US market only. Product names, forms and notes follow US usage (e.g. ISO homeowners HO-1 to HO-8 forms, ISO commercial forms, NCCI workers' comp, ACA/Medicare/Medicaid programs, USDA Risk Management Agency crop programs).
A35: Compiled from general industry knowledge of publicly documented US sources: ISO/Verisk standard policy forms, NAIC model laws and consumer guides, Insurance Information Institute (III) explainers, CMS/Medicare.gov, HealthCare.gov, FEMA/NFIP, USDA RMA, SSA, NCCI and IRS publications. Figures (limits, thresholds, dates) are as generally published at the time of writing and change over time; verify current values before relying on them.
A36: Terminology varies: insurers, states and agents often use different names for the same product (see the Also Known As column). Many products differ by state, because insurance is regulated mainly at the state level.
A37: The tree is a learning aid, not legal or buying advice. Some products fit more than one branch; each appears once in its most common home, and a few government programs are also listed under Social & Government Programs with a cross-reference.
A38: Counts in this sheet are live formulas over the Tree sheet, so they update if rows are added or removed.

Sheet README
A1: Insurance Taxonomy (US market)
A2: A tree of US insurance product types for people new to insurance: individuals, developers joining insurance projects, new underwriters and product owners. The same data is exported to data/insurance-taxonomy.csv for the app.
A4: Sheets
A5: Tree | B5: One row per node (product type or grouping), ordered depth-first so the tree reads top to bottom. This is the machine-readable source.
A6: Outline | B6: The same tree as an indented outline, one column per level. Use the +/- buttons or the 1-6 outline level buttons at the top left to collapse and expand branches.
A7: Summary | B7: Node counts per root category and per level (live formulas), plus notes on sources and approach.
A8: README | B8: This sheet.
A10: Columns in the Tree sheet
A11: ID | B11: Stable, unique, dot-separated identifier built from the parent's ID plus a short slug, e.g. life.permanent.universal.iul. Lowercase letters, digits and underscores only. Use it as the key in the app; do not rely on row numbers.
A12: Parent ID | B12: ID of the parent node. Blank for the 13 root categories. Every non-blank Parent ID exists as an ID in the sheet.
A13: Level | B13: Depth in the tree: 1 = root category, 2 = its children, and so on. Always equals the parent's level + 1.
A14: Name | B14: Display name. Indented visually by level in Excel (cell indent only; the value has no leading spaces).
A15: Also Known As | B15: Other names, abbreviations or brand/state names for the same thing, separated by semicolons. Blank if none.
A16: Plain-English Description | B16: One or two sentences in simple language.
A17: Example | B17: A concrete, real-life example of who buys it or what it pays for.
A18: Personal/Commercial/Both | B18: Whether it is bought mainly by individuals/families (Personal), businesses/organizations (Commercial) or both.
A19: US Notes | B19: US-specific details: state vs federal regulation, state variations, key laws, program names. Blank where not applicable.
A20: Full Path | B20: Names from the root down to this node, separated by ' > '. Always equals the parent's Full Path + ' > ' + Name.
A22: How the tree is linked
A23: Parent/child | B23: Each row points to its parent through Parent ID. To build the tree: create a node for each row keyed by ID, then attach each node to the node whose ID equals its Parent ID. Rows with a blank Parent ID are roots.
A24: ID prefixes | B24: Because IDs are built from the parent's ID, every descendant's ID starts with its ancestor's ID followed by a dot. For example, all Life nodes start with 'life.'; all universal life types start with 'life.permanent.universal.'.
A25: Ordering | B25: Rows are in depth-first (pre-order) order: a parent always appears before its children, and siblings appear in a teaching-friendly order.
A26: Validation | B26: The file was checked by script: IDs are unique, every Parent ID exists, Level = parent Level + 1, and Full Path = parent Full Path + ' > ' + Name.
A28: Caveat | B28: Educational reference only; not legal, tax or buying advice. Details vary by state and change over time.
